[{"setup": "\n<p>Consider the 2-player game described by the normal form below:</p>\n<table border=1px align=\"center\">\n  <tr>\n    <td></td>\n    <td></td>\n    <td colspan=2 align=\"center\">Player 2</td>\n  </tr>\n  <tr>\n    <td></td>\n    <td></td>\n    <td align=\"center\">A</td>\n    <td align=\"center\">B</td>\n  <tr>\n    <td rowspan=2>Player 1</td>\n    <td>A</td>\n    <td align=\"center\">1, 1</td>\n    <td align=\"center\">9, 0</td>\n  </tr>\n  <tr>\n    <td>B</td>\n    <td align=\"center\">0, 9</td>\n    <td align=\"center\">4, 4</td>\n  </tr>\n</table>\n\n<p>1. Write down the best response functions for each player.</p>\n<p>2. Find the Nash equilibria.</p>\n<p>3. Do the strategic dynamics of this game most resemble Prisoner's Dilemma, Stag Hunt, Chicken, or Rock Paper Scissors?</p>\n", "solution": "<p>Player 1's best response(s) to Player 2 choosing A are: ['A']</p>\n<p>Player 1's best response(s) to Player 2 choosing B are: ['A']</p>\n<p>Player 2's best response(s) to Player 1 choosing A are: ['A']</p>\n<p>Player 2's best response(s) to Player 1 choosing B are: ['A']</p>\n<p>There are 1 Nash equilibria: [('A', 'A')]</p><p>The game is most similar to Prisoner's Dilemma.<p>"}, {"setup": "\n<p>Consider the 2-player game described by the normal form below:</p>\n<table border=1px align=\"center\">\n  <tr>\n    <td></td>\n    <td></td>\n    <td colspan=2 align=\"center\">Player 2</td>\n  </tr>\n  <tr>\n    <td></td>\n    <td></td>\n    <td align=\"center\">A</td>\n    <td align=\"center\">B</td>\n  <tr>\n    <td rowspan=2>Player 1</td>\n    <td>A</td>\n    <td align=\"center\">0, 9</td>\n    <td align=\"center\">6, 6</td>\n  </tr>\n  <tr>\n    <td>B</td>\n    <td align=\"center\">3, 3</td>\n    <td align=\"center\">9, 0</td>\n  </tr>\n</table>\n\n<p>1. Write down the best response functions for each player.</p>\n<p>2. Find the Nash equilibria.</p>\n<p>3. Do the strategic dynamics of this game most resemble Prisoner's Dilemma, Stag Hunt, Chicken, or Rock Paper Scissors?</p>\n", "solution": "<p>Player 1's best response(s) to Player 2 choosing A are: ['B']</p>\n<p>Player 1's best response(s) to Player 2 choosing B are: ['B']</p>\n<p>Player 2's best response(s) to Player 1 choosing A are: ['A']</p>\n<p>Player 2's best response(s) to Player 1 choosing B are: ['A']</p>\n<p>There are 1 Nash equilibria: [('B', 'A')]</p><p>The game is most similar to Prisoner's Dilemma.<p>"}, {"setup": "\n<p>Consider the 2-player game described by the normal form below:</p>\n<table border=1px align=\"center\">\n  <tr>\n    <td></td>\n    <td></td>\n    <td colspan=2 align=\"center\">Player 2</td>\n  </tr>\n  <tr>\n    <td></td>\n    <td></td>\n    <td align=\"center\">A</td>\n    <td align=\"center\">B</td>\n  <tr>\n    <td rowspan=2>Player 1</td>\n    <td>A</td>\n    <td align=\"center\">9, 1</td>\n    <td align=\"center\">3, 3</td>\n  </tr>\n  <tr>\n    <td>B</td>\n    <td align=\"center\">6, 6</td>\n    <td align=\"center\">1, 9</td>\n  </tr>\n</table>\n\n<p>1. Write down the best response functions for each player.</p>\n<p>2. Find the Nash equilibria.</p>\n<p>3. Do the strategic dynamics of this game most resemble Prisoner's Dilemma, Stag Hunt, Chicken, or Rock Paper Scissors?</p>\n", "solution": "<p>Player 1's best response(s) to Player 2 choosing A are: ['A']</p>\n<p>Player 1's best response(s) to Player 2 choosing B are: ['A']</p>\n<p>Player 2's best response(s) to Player 1 choosing A are: ['B']</p>\n<p>Player 2's best response(s) to Player 1 choosing B are: ['B']</p>\n<p>There are 1 Nash equilibria: [('A', 'B')]</p><p>The game is most similar to Prisoner's Dilemma.<p>"}, {"setup": "\n<p>Consider the 2-player game described by the normal form below:</p>\n<table border=1px align=\"center\">\n  <tr>\n    <td></td>\n    <td></td>\n    <td colspan=2 align=\"center\">Player 2</td>\n  </tr>\n  <tr>\n    <td></td>\n    <td></td>\n    <td align=\"center\">A</td>\n    <td align=\"center\">B</td>\n  <tr>\n    <td rowspan=2>Player 1</td>\n    <td>A</td>\n    <td align=\"center\">8, 0</td>\n    <td align=\"center\">4, 4</td>\n  </tr>\n  <tr>\n    <td>B</td>\n    <td align=\"center\">6, 6</td>\n    <td align=\"center\">0, 8</td>\n  </tr>\n</table>\n\n<p>1. Write down the best response functions for each player.</p>\n<p>2. Find the Nash equilibria.</p>\n<p>3. Do the strategic dynamics of this game most resemble Prisoner's Dilemma, Stag Hunt, Chicken, or Rock Paper Scissors?</p>\n", "solution": "<p>Player 1's best response(s) to Player 2 choosing A are: ['A']</p>\n<p>Player 1's best response(s) to Player 2 choosing B are: ['A']</p>\n<p>Player 2's best response(s) to Player 1 choosing A are: ['B']</p>\n<p>Player 2's best response(s) to Player 1 choosing B are: ['B']</p>\n<p>There are 1 Nash equilibria: [('A', 'B')]</p><p>The game is most similar to Prisoner's Dilemma.<p>"}, {"setup": "\n<p>Consider the 2-player game described by the normal form below:</p>\n<table border=1px align=\"center\">\n  <tr>\n    <td></td>\n    <td></td>\n    <td colspan=2 align=\"center\">Player 2</td>\n  </tr>\n  <tr>\n    <td></td>\n    <td></td>\n    <td align=\"center\">A</td>\n    <td align=\"center\">B</td>\n  <tr>\n    <td rowspan=2>Player 1</td>\n    <td>A</td>\n    <td align=\"center\">7, 7</td>\n    <td align=\"center\">3, 9</td>\n  </tr>\n  <tr>\n    <td>B</td>\n    <td align=\"center\">9, 3</td>\n    <td align=\"center\">6, 6</td>\n  </tr>\n</table>\n\n<p>1. Write down the best response functions for each player.</p>\n<p>2. Find the Nash equilibria.</p>\n<p>3. Do the strategic dynamics of this game most resemble Prisoner's Dilemma, Stag Hunt, Chicken, or Rock Paper Scissors?</p>\n", "solution": "<p>Player 1's best response(s) to Player 2 choosing A are: ['B']</p>\n<p>Player 1's best response(s) to Player 2 choosing B are: ['B']</p>\n<p>Player 2's best response(s) to Player 1 choosing A are: ['B']</p>\n<p>Player 2's best response(s) to Player 1 choosing B are: ['B']</p>\n<p>There are 1 Nash equilibria: [('B', 'B')]</p><p>The game is most similar to Prisoner's Dilemma.<p>"}, {"setup": "\n<p>Consider the 2-player game described by the normal form below:</p>\n<table border=1px align=\"center\">\n  <tr>\n    <td></td>\n    <td></td>\n    <td colspan=2 align=\"center\">Player 2</td>\n  </tr>\n  <tr>\n    <td></td>\n    <td></td>\n    <td align=\"center\">A</td>\n    <td align=\"center\">B</td>\n  <tr>\n    <td rowspan=2>Player 1</td>\n    <td>A</td>\n    <td align=\"center\">1, 9</td>\n    <td align=\"center\">7, 7</td>\n  </tr>\n  <tr>\n    <td>B</td>\n    <td align=\"center\">3, 3</td>\n    <td align=\"center\">9, 1</td>\n  </tr>\n</table>\n\n<p>1. Write down the best response functions for each player.</p>\n<p>2. Find the Nash equilibria.</p>\n<p>3. Do the strategic dynamics of this game most resemble Prisoner's Dilemma, Stag Hunt, Chicken, or Rock Paper Scissors?</p>\n", "solution": "<p>Player 1's best response(s) to Player 2 choosing A are: ['B']</p>\n<p>Player 1's best response(s) to Player 2 choosing B are: ['B']</p>\n<p>Player 2's best response(s) to Player 1 choosing A are: ['A']</p>\n<p>Player 2's best response(s) to Player 1 choosing B are: ['A']</p>\n<p>There are 1 Nash equilibria: [('B', 'A')]</p><p>The game is most similar to Prisoner's Dilemma.<p>"}, {"setup": "\n<p>Consider the 2-player game described by the normal form below:</p>\n<table border=1px align=\"center\">\n  <tr>\n    <td></td>\n    <td></td>\n    <td colspan=2 align=\"center\">Player 2</td>\n  </tr>\n  <tr>\n    <td></td>\n    <td></td>\n    <td align=\"center\">A</td>\n    <td align=\"center\">B</td>\n  <tr>\n    <td rowspan=2>Player 1</td>\n    <td>A</td>\n    <td align=\"center\">2, 6</td>\n    <td align=\"center\">5, 5</td>\n  </tr>\n  <tr>\n    <td>B</td>\n    <td align=\"center\">4, 4</td>\n    <td align=\"center\">6, 2</td>\n  </tr>\n</table>\n\n<p>1. Write down the best response functions for each player.</p>\n<p>2. Find the Nash equilibria.</p>\n<p>3. Do the strategic dynamics of this game most resemble Prisoner's Dilemma, Stag Hunt, Chicken, or Rock Paper Scissors?</p>\n", "solution": "<p>Player 1's best response(s) to Player 2 choosing A are: ['B']</p>\n<p>Player 1's best response(s) to Player 2 choosing B are: ['B']</p>\n<p>Player 2's best response(s) to Player 1 choosing A are: ['A']</p>\n<p>Player 2's best response(s) to Player 1 choosing B are: ['A']</p>\n<p>There are 1 Nash equilibria: [('B', 'A')]</p><p>The game is most similar to Prisoner's Dilemma.<p>"}, {"setup": "\n<p>Consider the 2-player game described by the normal form below:</p>\n<table border=1px align=\"center\">\n  <tr>\n    <td></td>\n    <td></td>\n    <td colspan=2 align=\"center\">Player 2</td>\n  </tr>\n  <tr>\n    <td></td>\n    <td></td>\n    <td align=\"center\">A</td>\n    <td align=\"center\">B</td>\n  <tr>\n    <td rowspan=2>Player 1</td>\n    <td>A</td>\n    <td align=\"center\">8, 0</td>\n    <td align=\"center\">4, 4</td>\n  </tr>\n  <tr>\n    <td>B</td>\n    <td align=\"center\">7, 7</td>\n    <td align=\"center\">0, 8</td>\n  </tr>\n</table>\n\n<p>1. Write down the best response functions for each player.</p>\n<p>2. Find the Nash equilibria.</p>\n<p>3. Do the strategic dynamics of this game most resemble Prisoner's Dilemma, Stag Hunt, Chicken, or Rock Paper Scissors?</p>\n", "solution": "<p>Player 1's best response(s) to Player 2 choosing A are: ['A']</p>\n<p>Player 1's best response(s) to Player 2 choosing B are: ['A']</p>\n<p>Player 2's best response(s) to Player 1 choosing A are: ['B']</p>\n<p>Player 2's best response(s) to Player 1 choosing B are: ['B']</p>\n<p>There are 1 Nash equilibria: [('A', 'B')]</p><p>The game is most similar to Prisoner's Dilemma.<p>"}, {"setup": "\n<p>Consider the 2-player game described by the normal form below:</p>\n<table border=1px align=\"center\">\n  <tr>\n    <td></td>\n    <td></td>\n    <td colspan=2 align=\"center\">Player 2</td>\n  </tr>\n  <tr>\n    <td></td>\n    <td></td>\n    <td align=\"center\">A</td>\n    <td align=\"center\">B</td>\n  <tr>\n    <td rowspan=2>Player 1</td>\n    <td>A</td>\n    <td align=\"center\">2, 9</td>\n    <td align=\"center\">8, 8</td>\n  </tr>\n  <tr>\n    <td>B</td>\n    <td align=\"center\">6, 6</td>\n    <td align=\"center\">9, 2</td>\n  </tr>\n</table>\n\n<p>1. Write down the best response functions for each player.</p>\n<p>2. Find the Nash equilibria.</p>\n<p>3. Do the strategic dynamics of this game most resemble Prisoner's Dilemma, Stag Hunt, Chicken, or Rock Paper Scissors?</p>\n", "solution": "<p>Player 1's best response(s) to Player 2 choosing A are: ['B']</p>\n<p>Player 1's best response(s) to Player 2 choosing B are: ['B']</p>\n<p>Player 2's best response(s) to Player 1 choosing A are: ['A']</p>\n<p>Player 2's best response(s) to Player 1 choosing B are: ['A']</p>\n<p>There are 1 Nash equilibria: [('B', 'A')]</p><p>The game is most similar to Prisoner's Dilemma.<p>"}, {"setup": "\n<p>Consider the 2-player game described by the normal form below:</p>\n<table border=1px align=\"center\">\n  <tr>\n    <td></td>\n    <td></td>\n    <td colspan=2 align=\"center\">Player 2</td>\n  </tr>\n  <tr>\n    <td></td>\n    <td></td>\n    <td align=\"center\">A</td>\n    <td align=\"center\">B</td>\n  <tr>\n    <td rowspan=2>Player 1</td>\n    <td>A</td>\n    <td align=\"center\">7, 1</td>\n    <td align=\"center\">2, 2</td>\n  </tr>\n  <tr>\n    <td>B</td>\n    <td align=\"center\">3, 3</td>\n    <td align=\"center\">1, 7</td>\n  </tr>\n</table>\n\n<p>1. Write down the best response functions for each player.</p>\n<p>2. Find the Nash equilibria.</p>\n<p>3. Do the strategic dynamics of this game most resemble Prisoner's Dilemma, Stag Hunt, Chicken, or Rock Paper Scissors?</p>\n", "solution": "<p>Player 1's best response(s) to Player 2 choosing A are: ['A']</p>\n<p>Player 1's best response(s) to Player 2 choosing B are: ['A']</p>\n<p>Player 2's best response(s) to Player 1 choosing A are: ['B']</p>\n<p>Player 2's best response(s) to Player 1 choosing B are: ['B']</p>\n<p>There are 1 Nash equilibria: [('A', 'B')]</p><p>The game is most similar to Prisoner's Dilemma.<p>"}, {"setup": "\n<p>Consider the 2-player game described by the normal form below:</p>\n<table border=1px align=\"center\">\n  <tr>\n    <td></td>\n    <td></td>\n    <td colspan=2 align=\"center\">Player 2</td>\n  </tr>\n  <tr>\n    <td></td>\n    <td></td>\n    <td align=\"center\">A</td>\n    <td align=\"center\">B</td>\n  <tr>\n    <td rowspan=2>Player 1</td>\n    <td>A</td>\n    <td align=\"center\">5, 5</td>\n    <td align=\"center\">5, 0</td>\n  </tr>\n  <tr>\n    <td>B</td>\n    <td align=\"center\">0, 5</td>\n    <td align=\"center\">7, 7</td>\n  </tr>\n</table>\n\n<p>1. Write down the best response functions for each player.</p>\n<p>2. Find the Nash equilibria.</p>\n<p>3. Do the strategic dynamics of this game most resemble Prisoner's Dilemma, Stag Hunt, Chicken, or Rock Paper Scissors?</p>\n", "solution": "<p>Player 1's best response(s) to Player 2 choosing A are: ['A']</p>\n<p>Player 1's best response(s) to Player 2 choosing B are: ['B']</p>\n<p>Player 2's best response(s) to Player 1 choosing A are: ['A']</p>\n<p>Player 2's best response(s) to Player 1 choosing B are: ['B']</p>\n<p>There are 2 Nash equilibria: [('A', 'A'), ('B', 'B')]</p><p>The game is most similar to Stag Hunt.<p>"}, {"setup": "\n<p>Consider the 2-player game described by the normal form below:</p>\n<table border=1px align=\"center\">\n  <tr>\n    <td></td>\n    <td></td>\n    <td colspan=2 align=\"center\">Player 2</td>\n  </tr>\n  <tr>\n    <td></td>\n    <td></td>\n    <td align=\"center\">A</td>\n    <td align=\"center\">B</td>\n  <tr>\n    <td rowspan=2>Player 1</td>\n    <td>A</td>\n    <td align=\"center\">6, 0</td>\n    <td align=\"center\">6, 6</td>\n  </tr>\n  <tr>\n    <td>B</td>\n    <td align=\"center\">7, 7</td>\n    <td align=\"center\">0, 6</td>\n  </tr>\n</table>\n\n<p>1. Write down the best response functions for each player.</p>\n<p>2. Find the Nash equilibria.</p>\n<p>3. Do the strategic dynamics of this game most resemble Prisoner's Dilemma, Stag Hunt, Chicken, or Rock Paper Scissors?</p>\n", "solution": "<p>Player 1's best response(s) to Player 2 choosing A are: ['B']</p>\n<p>Player 1's best response(s) to Player 2 choosing B are: ['A']</p>\n<p>Player 2's best response(s) to Player 1 choosing A are: ['B']</p>\n<p>Player 2's best response(s) to Player 1 choosing B are: ['A']</p>\n<p>There are 2 Nash equilibria: [('A', 'B'), ('B', 'A')]</p><p>The game is most similar to Stag Hunt.<p>"}, {"setup": "\n<p>Consider the 2-player game described by the normal form below:</p>\n<table border=1px align=\"center\">\n  <tr>\n    <td></td>\n    <td></td>\n    <td colspan=2 align=\"center\">Player 2</td>\n  </tr>\n  <tr>\n    <td></td>\n    <td></td>\n    <td align=\"center\">A</td>\n    <td align=\"center\">B</td>\n  <tr>\n    <td rowspan=2>Player 1</td>\n    <td>A</td>\n    <td align=\"center\">7, 7</td>\n    <td align=\"center\">2, 4</td>\n  </tr>\n  <tr>\n    <td>B</td>\n    <td align=\"center\">2, 4</td>\n    <td align=\"center\">4, 4</td>\n  </tr>\n</table>\n\n<p>1. Write down the best response functions for each player.</p>\n<p>2. Find the Nash equilibria.</p>\n<p>3. Do the strategic dynamics of this game most resemble Prisoner's Dilemma, Stag Hunt, Chicken, or Rock Paper Scissors?</p>\n", "solution": "<p>Player 1's best response(s) to Player 2 choosing A are: ['A']</p>\n<p>Player 1's best response(s) to Player 2 choosing B are: ['B']</p>\n<p>Player 2's best response(s) to Player 1 choosing A are: ['A']</p>\n<p>Player 2's best response(s) to Player 1 choosing B are: ['A', 'B']</p>\n<p>There are 2 Nash equilibria: [('A', 'A'), ('B', 'B')]</p><p>The game is most similar to Stag Hunt.<p>"}, {"setup": "\n<p>Consider the 2-player game described by the normal form below:</p>\n<table border=1px align=\"center\">\n  <tr>\n    <td></td>\n    <td></td>\n    <td colspan=2 align=\"center\">Player 2</td>\n  </tr>\n  <tr>\n    <td></td>\n    <td></td>\n    <td align=\"center\">A</td>\n    <td align=\"center\">B</td>\n  <tr>\n    <td rowspan=2>Player 1</td>\n    <td>A</td>\n    <td align=\"center\">2, 5</td>\n    <td align=\"center\">9, 9</td>\n  </tr>\n  <tr>\n    <td>B</td>\n    <td align=\"center\">5, 5</td>\n    <td align=\"center\">5, 2</td>\n  </tr>\n</table>\n\n<p>1. Write down the best response functions for each player.</p>\n<p>2. Find the Nash equilibria.</p>\n<p>3. Do the strategic dynamics of this game most resemble Prisoner's Dilemma, Stag Hunt, Chicken, or Rock Paper Scissors?</p>\n", "solution": "<p>Player 1's best response(s) to Player 2 choosing A are: ['B']</p>\n<p>Player 1's best response(s) to Player 2 choosing B are: ['A']</p>\n<p>Player 2's best response(s) to Player 1 choosing A are: ['B']</p>\n<p>Player 2's best response(s) to Player 1 choosing B are: ['A']</p>\n<p>There are 2 Nash equilibria: [('A', 'B'), ('B', 'A')]</p><p>The game is most similar to Stag Hunt.<p>"}, {"setup": "\n<p>Consider the 2-player game described by the normal form below:</p>\n<table border=1px align=\"center\">\n  <tr>\n    <td></td>\n    <td></td>\n    <td colspan=2 align=\"center\">Player 2</td>\n  </tr>\n  <tr>\n    <td></td>\n    <td></td>\n    <td align=\"center\">A</td>\n    <td align=\"center\">B</td>\n  <tr>\n    <td rowspan=2>Player 1</td>\n    <td>A</td>\n    <td align=\"center\">9, 9</td>\n    <td align=\"center\">1, 7</td>\n  </tr>\n  <tr>\n    <td>B</td>\n    <td align=\"center\">1, 7</td>\n    <td align=\"center\">7, 7</td>\n  </tr>\n</table>\n\n<p>1. Write down the best response functions for each player.</p>\n<p>2. Find the Nash equilibria.</p>\n<p>3. Do the strategic dynamics of this game most resemble Prisoner's Dilemma, Stag Hunt, Chicken, or Rock Paper Scissors?</p>\n", "solution": "<p>Player 1's best response(s) to Player 2 choosing A are: ['A']</p>\n<p>Player 1's best response(s) to Player 2 choosing B are: ['B']</p>\n<p>Player 2's best response(s) to Player 1 choosing A are: ['A']</p>\n<p>Player 2's best response(s) to Player 1 choosing B are: ['A', 'B']</p>\n<p>There are 2 Nash equilibria: [('A', 'A'), ('B', 'B')]</p><p>The game is most similar to Stag Hunt.<p>"}, {"setup": "\n<p>Consider the 2-player game described by the normal form below:</p>\n<table border=1px align=\"center\">\n  <tr>\n    <td></td>\n    <td></td>\n    <td colspan=2 align=\"center\">Player 2</td>\n  </tr>\n  <tr>\n    <td></td>\n    <td></td>\n    <td align=\"center\">A</td>\n    <td align=\"center\">B</td>\n  <tr>\n    <td rowspan=2>Player 1</td>\n    <td>A</td>\n    <td align=\"center\">7, 4</td>\n    <td align=\"center\">7, 7</td>\n  </tr>\n  <tr>\n    <td>B</td>\n    <td align=\"center\">9, 9</td>\n    <td align=\"center\">4, 7</td>\n  </tr>\n</table>\n\n<p>1. Write down the best response functions for each player.</p>\n<p>2. Find the Nash equilibria.</p>\n<p>3. Do the strategic dynamics of this game most resemble Prisoner's Dilemma, Stag Hunt, Chicken, or Rock Paper Scissors?</p>\n", "solution": "<p>Player 1's best response(s) to Player 2 choosing A are: ['B']</p>\n<p>Player 1's best response(s) to Player 2 choosing B are: ['A']</p>\n<p>Player 2's best response(s) to Player 1 choosing A are: ['B']</p>\n<p>Player 2's best response(s) to Player 1 choosing B are: ['A']</p>\n<p>There are 2 Nash equilibria: [('A', 'B'), ('B', 'A')]</p><p>The game is most similar to Stag Hunt.<p>"}, {"setup": "\n<p>Consider the 2-player game described by the normal form below:</p>\n<table border=1px align=\"center\">\n  <tr>\n    <td></td>\n    <td></td>\n    <td colspan=2 align=\"center\">Player 2</td>\n  </tr>\n  <tr>\n    <td></td>\n    <td></td>\n    <td align=\"center\">A</td>\n    <td align=\"center\">B</td>\n  <tr>\n    <td rowspan=2>Player 1</td>\n    <td>A</td>\n    <td align=\"center\">4, 4</td>\n    <td align=\"center\">4, 3</td>\n  </tr>\n  <tr>\n    <td>B</td>\n    <td align=\"center\">3, 4</td>\n    <td align=\"center\">6, 6</td>\n  </tr>\n</table>\n\n<p>1. Write down the best response functions for each player.</p>\n<p>2. Find the Nash equilibria.</p>\n<p>3. Do the strategic dynamics of this game most resemble Prisoner's Dilemma, Stag Hunt, Chicken, or Rock Paper Scissors?</p>\n", "solution": "<p>Player 1's best response(s) to Player 2 choosing A are: ['A']</p>\n<p>Player 1's best response(s) to Player 2 choosing B are: ['B']</p>\n<p>Player 2's best response(s) to Player 1 choosing A are: ['A']</p>\n<p>Player 2's best response(s) to Player 1 choosing B are: ['B']</p>\n<p>There are 2 Nash equilibria: [('A', 'A'), ('B', 'B')]</p><p>The game is most similar to Stag Hunt.<p>"}, {"setup": "\n<p>Consider the 2-player game described by the normal form below:</p>\n<table border=1px align=\"center\">\n  <tr>\n    <td></td>\n    <td></td>\n    <td colspan=2 align=\"center\">Player 2</td>\n  </tr>\n  <tr>\n    <td></td>\n    <td></td>\n    <td align=\"center\">A</td>\n    <td align=\"center\">B</td>\n  <tr>\n    <td rowspan=2>Player 1</td>\n    <td>A</td>\n    <td align=\"center\">7, 7</td>\n    <td align=\"center\">7, 1</td>\n  </tr>\n  <tr>\n    <td>B</td>\n    <td align=\"center\">1, 7</td>\n    <td align=\"center\">9, 9</td>\n  </tr>\n</table>\n\n<p>1. Write down the best response functions for each player.</p>\n<p>2. Find the Nash equilibria.</p>\n<p>3. Do the strategic dynamics of this game most resemble Prisoner's Dilemma, Stag Hunt, Chicken, or Rock Paper Scissors?</p>\n", "solution": "<p>Player 1's best response(s) to Player 2 choosing A are: ['A']</p>\n<p>Player 1's best response(s) to Player 2 choosing B are: ['B']</p>\n<p>Player 2's best response(s) to Player 1 choosing A are: ['A']</p>\n<p>Player 2's best response(s) to Player 1 choosing B are: ['B']</p>\n<p>There are 2 Nash equilibria: [('A', 'A'), ('B', 'B')]</p><p>The game is most similar to Stag Hunt.<p>"}, {"setup": "\n<p>Consider the 2-player game described by the normal form below:</p>\n<table border=1px align=\"center\">\n  <tr>\n    <td></td>\n    <td></td>\n    <td colspan=2 align=\"center\">Player 2</td>\n  </tr>\n  <tr>\n    <td></td>\n    <td></td>\n    <td align=\"center\">A</td>\n    <td align=\"center\">B</td>\n  <tr>\n    <td rowspan=2>Player 1</td>\n    <td>A</td>\n    <td align=\"center\">0, 2</td>\n    <td align=\"center\">5, 5</td>\n  </tr>\n  <tr>\n    <td>B</td>\n    <td align=\"center\">2, 2</td>\n    <td align=\"center\">2, 0</td>\n  </tr>\n</table>\n\n<p>1. Write down the best response functions for each player.</p>\n<p>2. Find the Nash equilibria.</p>\n<p>3. Do the strategic dynamics of this game most resemble Prisoner's Dilemma, Stag Hunt, Chicken, or Rock Paper Scissors?</p>\n", "solution": "<p>Player 1's best response(s) to Player 2 choosing A are: ['B']</p>\n<p>Player 1's best response(s) to Player 2 choosing B are: ['A']</p>\n<p>Player 2's best response(s) to Player 1 choosing A are: ['B']</p>\n<p>Player 2's best response(s) to Player 1 choosing B are: ['A']</p>\n<p>There are 2 Nash equilibria: [('A', 'B'), ('B', 'A')]</p><p>The game is most similar to Stag Hunt.<p>"}, {"setup": "\n<p>Consider the 2-player game described by the normal form below:</p>\n<table border=1px align=\"center\">\n  <tr>\n    <td></td>\n    <td></td>\n    <td colspan=2 align=\"center\">Player 2</td>\n  </tr>\n  <tr>\n    <td></td>\n    <td></td>\n    <td align=\"center\">A</td>\n    <td align=\"center\">B</td>\n  <tr>\n    <td rowspan=2>Player 1</td>\n    <td>A</td>\n    <td align=\"center\">3, 0</td>\n    <td align=\"center\">3, 3</td>\n  </tr>\n  <tr>\n    <td>B</td>\n    <td align=\"center\">4, 4</td>\n    <td align=\"center\">0, 3</td>\n  </tr>\n</table>\n\n<p>1. Write down the best response functions for each player.</p>\n<p>2. Find the Nash equilibria.</p>\n<p>3. Do the strategic dynamics of this game most resemble Prisoner's Dilemma, Stag Hunt, Chicken, or Rock Paper Scissors?</p>\n", "solution": "<p>Player 1's best response(s) to Player 2 choosing A are: ['B']</p>\n<p>Player 1's best response(s) to Player 2 choosing B are: ['A']</p>\n<p>Player 2's best response(s) to Player 1 choosing A are: ['B']</p>\n<p>Player 2's best response(s) to Player 1 choosing B are: ['A']</p>\n<p>There are 2 Nash equilibria: [('A', 'B'), ('B', 'A')]</p><p>The game is most similar to Stag Hunt.<p>"}, {"setup": "\n<p>Consider the 2-player game described by the normal form below:</p>\n<table border=1px align=\"center\">\n  <tr>\n    <td></td>\n    <td></td>\n    <td colspan=2 align=\"center\">Player 2</td>\n  </tr>\n  <tr>\n    <td></td>\n    <td></td>\n    <td align=\"center\">A</td>\n    <td align=\"center\">B</td>\n  <tr>\n    <td rowspan=2>Player 1</td>\n    <td>A</td>\n    <td align=\"center\">5, 7</td>\n    <td align=\"center\">6, 6</td>\n  </tr>\n  <tr>\n    <td>B</td>\n    <td align=\"center\">4, 4</td>\n    <td align=\"center\">7, 5</td>\n  </tr>\n</table>\n\n<p>1. Write down the best response functions for each player.</p>\n<p>2. Find the Nash equilibria.</p>\n<p>3. Do the strategic dynamics of this game most resemble Prisoner's Dilemma, Stag Hunt, Chicken, or Rock Paper Scissors?</p>\n", "solution": "<p>Player 1's best response(s) to Player 2 choosing A are: ['A']</p>\n<p>Player 1's best response(s) to Player 2 choosing B are: ['B']</p>\n<p>Player 2's best response(s) to Player 1 choosing A are: ['A']</p>\n<p>Player 2's best response(s) to Player 1 choosing B are: ['B']</p>\n<p>There are 2 Nash equilibria: [('A', 'A'), ('B', 'B')]</p><p>The game is most similar to Chicken.<p>"}, {"setup": "\n<p>Consider the 2-player game described by the normal form below:</p>\n<table border=1px align=\"center\">\n  <tr>\n    <td></td>\n    <td></td>\n    <td colspan=2 align=\"center\">Player 2</td>\n  </tr>\n  <tr>\n    <td></td>\n    <td></td>\n    <td align=\"center\">A</td>\n    <td align=\"center\">B</td>\n  <tr>\n    <td rowspan=2>Player 1</td>\n    <td>A</td>\n    <td align=\"center\">5, 7</td>\n    <td align=\"center\">6, 6</td>\n  </tr>\n  <tr>\n    <td>B</td>\n    <td align=\"center\">1, 1</td>\n    <td align=\"center\">7, 5</td>\n  </tr>\n</table>\n\n<p>1. Write down the best response functions for each player.</p>\n<p>2. Find the Nash equilibria.</p>\n<p>3. Do the strategic dynamics of this game most resemble Prisoner's Dilemma, Stag Hunt, Chicken, or Rock Paper Scissors?</p>\n", "solution": "<p>Player 1's best response(s) to Player 2 choosing A are: ['A']</p>\n<p>Player 1's best response(s) to Player 2 choosing B are: ['B']</p>\n<p>Player 2's best response(s) to Player 1 choosing A are: ['A']</p>\n<p>Player 2's best response(s) to Player 1 choosing B are: ['B']</p>\n<p>There are 2 Nash equilibria: [('A', 'A'), ('B', 'B')]</p><p>The game is most similar to Chicken.<p>"}, {"setup": "\n<p>Consider the 2-player game described by the normal form below:</p>\n<table border=1px align=\"center\">\n  <tr>\n    <td></td>\n    <td></td>\n    <td colspan=2 align=\"center\">Player 2</td>\n  </tr>\n  <tr>\n    <td></td>\n    <td></td>\n    <td align=\"center\">A</td>\n    <td align=\"center\">B</td>\n  <tr>\n    <td rowspan=2>Player 1</td>\n    <td>A</td>\n    <td align=\"center\">5, 5</td>\n    <td align=\"center\">4, 9</td>\n  </tr>\n  <tr>\n    <td>B</td>\n    <td align=\"center\">9, 4</td>\n    <td align=\"center\">0, 0</td>\n  </tr>\n</table>\n\n<p>1. Write down the best response functions for each player.</p>\n<p>2. Find the Nash equilibria.</p>\n<p>3. Do the strategic dynamics of this game most resemble Prisoner's Dilemma, Stag Hunt, Chicken, or Rock Paper Scissors?</p>\n", "solution": "<p>Player 1's best response(s) to Player 2 choosing A are: ['B']</p>\n<p>Player 1's best response(s) to Player 2 choosing B are: ['A']</p>\n<p>Player 2's best response(s) to Player 1 choosing A are: ['B']</p>\n<p>Player 2's best response(s) to Player 1 choosing B are: ['A']</p>\n<p>There are 2 Nash equilibria: [('A', 'B'), ('B', 'A')]</p><p>The game is most similar to Chicken.<p>"}, {"setup": "\n<p>Consider the 2-player game described by the normal form below:</p>\n<table border=1px align=\"center\">\n  <tr>\n    <td></td>\n    <td></td>\n    <td colspan=2 align=\"center\">Player 2</td>\n  </tr>\n  <tr>\n    <td></td>\n    <td></td>\n    <td align=\"center\">A</td>\n    <td align=\"center\">B</td>\n  <tr>\n    <td rowspan=2>Player 1</td>\n    <td>A</td>\n    <td align=\"center\">9, 6</td>\n    <td align=\"center\">4, 4</td>\n  </tr>\n  <tr>\n    <td>B</td>\n    <td align=\"center\">8, 8</td>\n    <td align=\"center\">6, 9</td>\n  </tr>\n</table>\n\n<p>1. Write down the best response functions for each player.</p>\n<p>2. Find the Nash equilibria.</p>\n<p>3. Do the strategic dynamics of this game most resemble Prisoner's Dilemma, Stag Hunt, Chicken, or Rock Paper Scissors?</p>\n", "solution": "<p>Player 1's best response(s) to Player 2 choosing A are: ['A']</p>\n<p>Player 1's best response(s) to Player 2 choosing B are: ['B']</p>\n<p>Player 2's best response(s) to Player 1 choosing A are: ['A']</p>\n<p>Player 2's best response(s) to Player 1 choosing B are: ['B']</p>\n<p>There are 2 Nash equilibria: [('A', 'A'), ('B', 'B')]</p><p>The game is most similar to Chicken.<p>"}, {"setup": "\n<p>Consider the 2-player game described by the normal form below:</p>\n<table border=1px align=\"center\">\n  <tr>\n    <td></td>\n    <td></td>\n    <td colspan=2 align=\"center\">Player 2</td>\n  </tr>\n  <tr>\n    <td></td>\n    <td></td>\n    <td align=\"center\">A</td>\n    <td align=\"center\">B</td>\n  <tr>\n    <td rowspan=2>Player 1</td>\n    <td>A</td>\n    <td align=\"center\">9, 4</td>\n    <td align=\"center\">0, 0</td>\n  </tr>\n  <tr>\n    <td>B</td>\n    <td align=\"center\">7, 7</td>\n    <td align=\"center\">4, 9</td>\n  </tr>\n</table>\n\n<p>1. Write down the best response functions for each player.</p>\n<p>2. Find the Nash equilibria.</p>\n<p>3. Do the strategic dynamics of this game most resemble Prisoner's Dilemma, Stag Hunt, Chicken, or Rock Paper Scissors?</p>\n", "solution": "<p>Player 1's best response(s) to Player 2 choosing A are: ['A']</p>\n<p>Player 1's best response(s) to Player 2 choosing B are: ['B']</p>\n<p>Player 2's best response(s) to Player 1 choosing A are: ['A']</p>\n<p>Player 2's best response(s) to Player 1 choosing B are: ['B']</p>\n<p>There are 2 Nash equilibria: [('A', 'A'), ('B', 'B')]</p><p>The game is most similar to Chicken.<p>"}, {"setup": "\n<p>Consider the 2-player game described by the normal form below:</p>\n<table border=1px align=\"center\">\n  <tr>\n    <td></td>\n    <td></td>\n    <td colspan=2 align=\"center\">Player 2</td>\n  </tr>\n  <tr>\n    <td></td>\n    <td></td>\n    <td align=\"center\">A</td>\n    <td align=\"center\">B</td>\n  <tr>\n    <td rowspan=2>Player 1</td>\n    <td>A</td>\n    <td align=\"center\">9, 3</td>\n    <td align=\"center\">2, 2</td>\n  </tr>\n  <tr>\n    <td>B</td>\n    <td align=\"center\">5, 5</td>\n    <td align=\"center\">3, 9</td>\n  </tr>\n</table>\n\n<p>1. Write down the best response functions for each player.</p>\n<p>2. Find the Nash equilibria.</p>\n<p>3. Do the strategic dynamics of this game most resemble Prisoner's Dilemma, Stag Hunt, Chicken, or Rock Paper Scissors?</p>\n", "solution": "<p>Player 1's best response(s) to Player 2 choosing A are: ['A']</p>\n<p>Player 1's best response(s) to Player 2 choosing B are: ['B']</p>\n<p>Player 2's best response(s) to Player 1 choosing A are: ['A']</p>\n<p>Player 2's best response(s) to Player 1 choosing B are: ['B']</p>\n<p>There are 2 Nash equilibria: [('A', 'A'), ('B', 'B')]</p><p>The game is most similar to Chicken.<p>"}, {"setup": "\n<p>Consider the 2-player game described by the normal form below:</p>\n<table border=1px align=\"center\">\n  <tr>\n    <td></td>\n    <td></td>\n    <td colspan=2 align=\"center\">Player 2</td>\n  </tr>\n  <tr>\n    <td></td>\n    <td></td>\n    <td align=\"center\">A</td>\n    <td align=\"center\">B</td>\n  <tr>\n    <td rowspan=2>Player 1</td>\n    <td>A</td>\n    <td align=\"center\">6, 8</td>\n    <td align=\"center\">7, 7</td>\n  </tr>\n  <tr>\n    <td>B</td>\n    <td align=\"center\">2, 2</td>\n    <td align=\"center\">8, 6</td>\n  </tr>\n</table>\n\n<p>1. Write down the best response functions for each player.</p>\n<p>2. Find the Nash equilibria.</p>\n<p>3. Do the strategic dynamics of this game most resemble Prisoner's Dilemma, Stag Hunt, Chicken, or Rock Paper Scissors?</p>\n", "solution": "<p>Player 1's best response(s) to Player 2 choosing A are: ['A']</p>\n<p>Player 1's best response(s) to Player 2 choosing B are: ['B']</p>\n<p>Player 2's best response(s) to Player 1 choosing A are: ['A']</p>\n<p>Player 2's best response(s) to Player 1 choosing B are: ['B']</p>\n<p>There are 2 Nash equilibria: [('A', 'A'), ('B', 'B')]</p><p>The game is most similar to Chicken.<p>"}, {"setup": "\n<p>Consider the 2-player game described by the normal form below:</p>\n<table border=1px align=\"center\">\n  <tr>\n    <td></td>\n    <td></td>\n    <td colspan=2 align=\"center\">Player 2</td>\n  </tr>\n  <tr>\n    <td></td>\n    <td></td>\n    <td align=\"center\">A</td>\n    <td align=\"center\">B</td>\n  <tr>\n    <td rowspan=2>Player 1</td>\n    <td>A</td>\n    <td align=\"center\">4, 4</td>\n    <td align=\"center\">3, 8</td>\n  </tr>\n  <tr>\n    <td>B</td>\n    <td align=\"center\">8, 3</td>\n    <td align=\"center\">1, 1</td>\n  </tr>\n</table>\n\n<p>1. Write down the best response functions for each player.</p>\n<p>2. Find the Nash equilibria.</p>\n<p>3. Do the strategic dynamics of this game most resemble Prisoner's Dilemma, Stag Hunt, Chicken, or Rock Paper Scissors?</p>\n", "solution": "<p>Player 1's best response(s) to Player 2 choosing A are: ['B']</p>\n<p>Player 1's best response(s) to Player 2 choosing B are: ['A']</p>\n<p>Player 2's best response(s) to Player 1 choosing A are: ['B']</p>\n<p>Player 2's best response(s) to Player 1 choosing B are: ['A']</p>\n<p>There are 2 Nash equilibria: [('A', 'B'), ('B', 'A')]</p><p>The game is most similar to Chicken.<p>"}, {"setup": "\n<p>Consider the 2-player game described by the normal form below:</p>\n<table border=1px align=\"center\">\n  <tr>\n    <td></td>\n    <td></td>\n    <td colspan=2 align=\"center\">Player 2</td>\n  </tr>\n  <tr>\n    <td></td>\n    <td></td>\n    <td align=\"center\">A</td>\n    <td align=\"center\">B</td>\n  <tr>\n    <td rowspan=2>Player 1</td>\n    <td>A</td>\n    <td align=\"center\">5, 5</td>\n    <td align=\"center\">8, 6</td>\n  </tr>\n  <tr>\n    <td>B</td>\n    <td align=\"center\">6, 8</td>\n    <td align=\"center\">7, 7</td>\n  </tr>\n</table>\n\n<p>1. Write down the best response functions for each player.</p>\n<p>2. Find the Nash equilibria.</p>\n<p>3. Do the strategic dynamics of this game most resemble Prisoner's Dilemma, Stag Hunt, Chicken, or Rock Paper Scissors?</p>\n", "solution": "<p>Player 1's best response(s) to Player 2 choosing A are: ['B']</p>\n<p>Player 1's best response(s) to Player 2 choosing B are: ['A']</p>\n<p>Player 2's best response(s) to Player 1 choosing A are: ['B']</p>\n<p>Player 2's best response(s) to Player 1 choosing B are: ['A']</p>\n<p>There are 2 Nash equilibria: [('A', 'B'), ('B', 'A')]</p><p>The game is most similar to Chicken.<p>"}, {"setup": "\n<p>Consider the 2-player game described by the normal form below:</p>\n<table border=1px align=\"center\">\n  <tr>\n    <td></td>\n    <td></td>\n    <td colspan=2 align=\"center\">Player 2</td>\n  </tr>\n  <tr>\n    <td></td>\n    <td></td>\n    <td align=\"center\">A</td>\n    <td align=\"center\">B</td>\n  <tr>\n    <td rowspan=2>Player 1</td>\n    <td>A</td>\n    <td align=\"center\">9, 7</td>\n    <td align=\"center\">3, 3</td>\n  </tr>\n  <tr>\n    <td>B</td>\n    <td align=\"center\">8, 8</td>\n    <td align=\"center\">7, 9</td>\n  </tr>\n</table>\n\n<p>1. Write down the best response functions for each player.</p>\n<p>2. Find the Nash equilibria.</p>\n<p>3. Do the strategic dynamics of this game most resemble Prisoner's Dilemma, Stag Hunt, Chicken, or Rock Paper Scissors?</p>\n", "solution": "<p>Player 1's best response(s) to Player 2 choosing A are: ['A']</p>\n<p>Player 1's best response(s) to Player 2 choosing B are: ['B']</p>\n<p>Player 2's best response(s) to Player 1 choosing A are: ['A']</p>\n<p>Player 2's best response(s) to Player 1 choosing B are: ['B']</p>\n<p>There are 2 Nash equilibria: [('A', 'A'), ('B', 'B')]</p><p>The game is most similar to Chicken.<p>"}, {"setup": "\n<p>Consider the 2-player game described by the normal form below:</p>\n<table border=1px align=\"center\">\n  <tr>\n    <td></td>\n    <td></td>\n    <td colspan=2 align=\"center\">Player 2</td>\n  </tr>\n  <tr>\n    <td></td>\n    <td></td>\n    <td align=\"center\">A</td>\n    <td align=\"center\">B</td>\n  <tr>\n    <td rowspan=2>Player 1</td>\n    <td>A</td>\n    <td align=\"center\">-9, 9</td>\n    <td align=\"center\">9, -9</td>\n  </tr>\n  <tr>\n    <td>B</td>\n    <td align=\"center\">9, -9</td>\n    <td align=\"center\">-9, 9</td>\n  </tr>\n</table>\n\n<p>1. Write down the best response functions for each player.</p>\n<p>2. Find the Nash equilibria.</p>\n<p>3. Do the strategic dynamics of this game most resemble Prisoner's Dilemma, Stag Hunt, Chicken, or Rock Paper Scissors?</p>\n", "solution": "<p>Player 1's best response(s) to Player 2 choosing A are: ['B']</p>\n<p>Player 1's best response(s) to Player 2 choosing B are: ['A']</p>\n<p>Player 2's best response(s) to Player 1 choosing A are: ['A']</p>\n<p>Player 2's best response(s) to Player 1 choosing B are: ['B']</p>\n<p>There are 0 Nash equilibria: []</p><p>The game is most similar to Rock Paper Scissors.<p>"}, {"setup": "\n<p>Consider the 2-player game described by the normal form below:</p>\n<table border=1px align=\"center\">\n  <tr>\n    <td></td>\n    <td></td>\n    <td colspan=2 align=\"center\">Player 2</td>\n  </tr>\n  <tr>\n    <td></td>\n    <td></td>\n    <td align=\"center\">A</td>\n    <td align=\"center\">B</td>\n  <tr>\n    <td rowspan=2>Player 1</td>\n    <td>A</td>\n    <td align=\"center\">4, 8</td>\n    <td align=\"center\">8, 4</td>\n  </tr>\n  <tr>\n    <td>B</td>\n    <td align=\"center\">8, 4</td>\n    <td align=\"center\">4, 8</td>\n  </tr>\n</table>\n\n<p>1. Write down the best response functions for each player.</p>\n<p>2. Find the Nash equilibria.</p>\n<p>3. Do the strategic dynamics of this game most resemble Prisoner's Dilemma, Stag Hunt, Chicken, or Rock Paper Scissors?</p>\n", "solution": "<p>Player 1's best response(s) to Player 2 choosing A are: ['B']</p>\n<p>Player 1's best response(s) to Player 2 choosing B are: ['A']</p>\n<p>Player 2's best response(s) to Player 1 choosing A are: ['A']</p>\n<p>Player 2's best response(s) to Player 1 choosing B are: ['B']</p>\n<p>There are 0 Nash equilibria: []</p><p>The game is most similar to Rock Paper Scissors.<p>"}, {"setup": "\n<p>Consider the 2-player game described by the normal form below:</p>\n<table border=1px align=\"center\">\n  <tr>\n    <td></td>\n    <td></td>\n    <td colspan=2 align=\"center\">Player 2</td>\n  </tr>\n  <tr>\n    <td></td>\n    <td></td>\n    <td align=\"center\">A</td>\n    <td align=\"center\">B</td>\n  <tr>\n    <td rowspan=2>Player 1</td>\n    <td>A</td>\n    <td align=\"center\">1, 3</td>\n    <td align=\"center\">3, 1</td>\n  </tr>\n  <tr>\n    <td>B</td>\n    <td align=\"center\">3, 1</td>\n    <td align=\"center\">1, 3</td>\n  </tr>\n</table>\n\n<p>1. Write down the best response functions for each player.</p>\n<p>2. Find the Nash equilibria.</p>\n<p>3. Do the strategic dynamics of this game most resemble Prisoner's Dilemma, Stag Hunt, Chicken, or Rock Paper Scissors?</p>\n", "solution": "<p>Player 1's best response(s) to Player 2 choosing A are: ['B']</p>\n<p>Player 1's best response(s) to Player 2 choosing B are: ['A']</p>\n<p>Player 2's best response(s) to Player 1 choosing A are: ['A']</p>\n<p>Player 2's best response(s) to Player 1 choosing B are: ['B']</p>\n<p>There are 0 Nash equilibria: []</p><p>The game is most similar to Rock Paper Scissors.<p>"}, {"setup": "\n<p>Consider the 2-player game described by the normal form below:</p>\n<table border=1px align=\"center\">\n  <tr>\n    <td></td>\n    <td></td>\n    <td colspan=2 align=\"center\">Player 2</td>\n  </tr>\n  <tr>\n    <td></td>\n    <td></td>\n    <td align=\"center\">A</td>\n    <td align=\"center\">B</td>\n  <tr>\n    <td rowspan=2>Player 1</td>\n    <td>A</td>\n    <td align=\"center\">8, -6</td>\n    <td align=\"center\">-6, 8</td>\n  </tr>\n  <tr>\n    <td>B</td>\n    <td align=\"center\">-6, 8</td>\n    <td align=\"center\">8, -6</td>\n  </tr>\n</table>\n\n<p>1. Write down the best response functions for each player.</p>\n<p>2. Find the Nash equilibria.</p>\n<p>3. Do the strategic dynamics of this game most resemble Prisoner's Dilemma, Stag Hunt, Chicken, or Rock Paper Scissors?</p>\n", "solution": "<p>Player 1's best response(s) to Player 2 choosing A are: ['A']</p>\n<p>Player 1's best response(s) to Player 2 choosing B are: ['B']</p>\n<p>Player 2's best response(s) to Player 1 choosing A are: ['B']</p>\n<p>Player 2's best response(s) to Player 1 choosing B are: ['A']</p>\n<p>There are 0 Nash equilibria: []</p><p>The game is most similar to Rock Paper Scissors.<p>"}, {"setup": "\n<p>Consider the 2-player game described by the normal form below:</p>\n<table border=1px align=\"center\">\n  <tr>\n    <td></td>\n    <td></td>\n    <td colspan=2 align=\"center\">Player 2</td>\n  </tr>\n  <tr>\n    <td></td>\n    <td></td>\n    <td align=\"center\">A</td>\n    <td align=\"center\">B</td>\n  <tr>\n    <td rowspan=2>Player 1</td>\n    <td>A</td>\n    <td align=\"center\">0, 9</td>\n    <td align=\"center\">9, 0</td>\n  </tr>\n  <tr>\n    <td>B</td>\n    <td align=\"center\">9, 0</td>\n    <td align=\"center\">0, 9</td>\n  </tr>\n</table>\n\n<p>1. Write down the best response functions for each player.</p>\n<p>2. Find the Nash equilibria.</p>\n<p>3. Do the strategic dynamics of this game most resemble Prisoner's Dilemma, Stag Hunt, Chicken, or Rock Paper Scissors?</p>\n", "solution": "<p>Player 1's best response(s) to Player 2 choosing A are: ['B']</p>\n<p>Player 1's best response(s) to Player 2 choosing B are: ['A']</p>\n<p>Player 2's best response(s) to Player 1 choosing A are: ['A']</p>\n<p>Player 2's best response(s) to Player 1 choosing B are: ['B']</p>\n<p>There are 0 Nash equilibria: []</p><p>The game is most similar to Rock Paper Scissors.<p>"}, {"setup": "\n<p>Consider the 2-player game described by the normal form below:</p>\n<table border=1px align=\"center\">\n  <tr>\n    <td></td>\n    <td></td>\n    <td colspan=2 align=\"center\">Player 2</td>\n  </tr>\n  <tr>\n    <td></td>\n    <td></td>\n    <td align=\"center\">A</td>\n    <td align=\"center\">B</td>\n  <tr>\n    <td rowspan=2>Player 1</td>\n    <td>A</td>\n    <td align=\"center\">7, 5</td>\n    <td align=\"center\">5, 7</td>\n  </tr>\n  <tr>\n    <td>B</td>\n    <td align=\"center\">5, 7</td>\n    <td align=\"center\">7, 5</td>\n  </tr>\n</table>\n\n<p>1. Write down the best response functions for each player.</p>\n<p>2. Find the Nash equilibria.</p>\n<p>3. Do the strategic dynamics of this game most resemble Prisoner's Dilemma, Stag Hunt, Chicken, or Rock Paper Scissors?</p>\n", "solution": "<p>Player 1's best response(s) to Player 2 choosing A are: ['A']</p>\n<p>Player 1's best response(s) to Player 2 choosing B are: ['B']</p>\n<p>Player 2's best response(s) to Player 1 choosing A are: ['B']</p>\n<p>Player 2's best response(s) to Player 1 choosing B are: ['A']</p>\n<p>There are 0 Nash equilibria: []</p><p>The game is most similar to Rock Paper Scissors.<p>"}, {"setup": "\n<p>Consider the 2-player game described by the normal form below:</p>\n<table border=1px align=\"center\">\n  <tr>\n    <td></td>\n    <td></td>\n    <td colspan=2 align=\"center\">Player 2</td>\n  </tr>\n  <tr>\n    <td></td>\n    <td></td>\n    <td align=\"center\">A</td>\n    <td align=\"center\">B</td>\n  <tr>\n    <td rowspan=2>Player 1</td>\n    <td>A</td>\n    <td align=\"center\">2, -2</td>\n    <td align=\"center\">-2, 2</td>\n  </tr>\n  <tr>\n    <td>B</td>\n    <td align=\"center\">-2, 2</td>\n    <td align=\"center\">2, -2</td>\n  </tr>\n</table>\n\n<p>1. Write down the best response functions for each player.</p>\n<p>2. Find the Nash equilibria.</p>\n<p>3. Do the strategic dynamics of this game most resemble Prisoner's Dilemma, Stag Hunt, Chicken, or Rock Paper Scissors?</p>\n", "solution": "<p>Player 1's best response(s) to Player 2 choosing A are: ['A']</p>\n<p>Player 1's best response(s) to Player 2 choosing B are: ['B']</p>\n<p>Player 2's best response(s) to Player 1 choosing A are: ['B']</p>\n<p>Player 2's best response(s) to Player 1 choosing B are: ['A']</p>\n<p>There are 0 Nash equilibria: []</p><p>The game is most similar to Rock Paper Scissors.<p>"}, {"setup": "\n<p>Consider the 2-player game described by the normal form below:</p>\n<table border=1px align=\"center\">\n  <tr>\n    <td></td>\n    <td></td>\n    <td colspan=2 align=\"center\">Player 2</td>\n  </tr>\n  <tr>\n    <td></td>\n    <td></td>\n    <td align=\"center\">A</td>\n    <td align=\"center\">B</td>\n  <tr>\n    <td rowspan=2>Player 1</td>\n    <td>A</td>\n    <td align=\"center\">-4, 4</td>\n    <td align=\"center\">4, -4</td>\n  </tr>\n  <tr>\n    <td>B</td>\n    <td align=\"center\">4, -4</td>\n    <td align=\"center\">-4, 4</td>\n  </tr>\n</table>\n\n<p>1. Write down the best response functions for each player.</p>\n<p>2. Find the Nash equilibria.</p>\n<p>3. Do the strategic dynamics of this game most resemble Prisoner's Dilemma, Stag Hunt, Chicken, or Rock Paper Scissors?</p>\n", "solution": "<p>Player 1's best response(s) to Player 2 choosing A are: ['B']</p>\n<p>Player 1's best response(s) to Player 2 choosing B are: ['A']</p>\n<p>Player 2's best response(s) to Player 1 choosing A are: ['A']</p>\n<p>Player 2's best response(s) to Player 1 choosing B are: ['B']</p>\n<p>There are 0 Nash equilibria: []</p><p>The game is most similar to Rock Paper Scissors.<p>"}, {"setup": "\n<p>Consider the 2-player game described by the normal form below:</p>\n<table border=1px align=\"center\">\n  <tr>\n    <td></td>\n    <td></td>\n    <td colspan=2 align=\"center\">Player 2</td>\n  </tr>\n  <tr>\n    <td></td>\n    <td></td>\n    <td align=\"center\">A</td>\n    <td align=\"center\">B</td>\n  <tr>\n    <td rowspan=2>Player 1</td>\n    <td>A</td>\n    <td align=\"center\">7, 1</td>\n    <td align=\"center\">1, 7</td>\n  </tr>\n  <tr>\n    <td>B</td>\n    <td align=\"center\">1, 7</td>\n    <td align=\"center\">7, 1</td>\n  </tr>\n</table>\n\n<p>1. Write down the best response functions for each player.</p>\n<p>2. Find the Nash equilibria.</p>\n<p>3. Do the strategic dynamics of this game most resemble Prisoner's Dilemma, Stag Hunt, Chicken, or Rock Paper Scissors?</p>\n", "solution": "<p>Player 1's best response(s) to Player 2 choosing A are: ['A']</p>\n<p>Player 1's best response(s) to Player 2 choosing B are: ['B']</p>\n<p>Player 2's best response(s) to Player 1 choosing A are: ['B']</p>\n<p>Player 2's best response(s) to Player 1 choosing B are: ['A']</p>\n<p>There are 0 Nash equilibria: []</p><p>The game is most similar to Rock Paper Scissors.<p>"}, {"setup": "\n<p>Consider the 2-player game described by the normal form below:</p>\n<table border=1px align=\"center\">\n  <tr>\n    <td></td>\n    <td></td>\n    <td colspan=2 align=\"center\">Player 2</td>\n  </tr>\n  <tr>\n    <td></td>\n    <td></td>\n    <td align=\"center\">A</td>\n    <td align=\"center\">B</td>\n  <tr>\n    <td rowspan=2>Player 1</td>\n    <td>A</td>\n    <td align=\"center\">0, 4</td>\n    <td align=\"center\">4, 0</td>\n  </tr>\n  <tr>\n    <td>B</td>\n    <td align=\"center\">4, 0</td>\n    <td align=\"center\">0, 4</td>\n  </tr>\n</table>\n\n<p>1. Write down the best response functions for each player.</p>\n<p>2. Find the Nash equilibria.</p>\n<p>3. Do the strategic dynamics of this game most resemble Prisoner's Dilemma, Stag Hunt, Chicken, or Rock Paper Scissors?</p>\n", "solution": "<p>Player 1's best response(s) to Player 2 choosing A are: ['B']</p>\n<p>Player 1's best response(s) to Player 2 choosing B are: ['A']</p>\n<p>Player 2's best response(s) to Player 1 choosing A are: ['A']</p>\n<p>Player 2's best response(s) to Player 1 choosing B are: ['B']</p>\n<p>There are 0 Nash equilibria: []</p><p>The game is most similar to Rock Paper Scissors.<p>"}, {"setup": "\n<p>Consider the 2-player game described by the normal form below:</p>\n<table border=1px align=\"center\">\n  <tr>\n    <td></td>\n    <td></td>\n    <td colspan=2 align=\"center\">Player 2</td>\n  </tr>\n  <tr>\n    <td></td>\n    <td></td>\n    <td align=\"center\">A</td>\n    <td align=\"center\">B</td>\n  <tr>\n    <td rowspan=2>Player 1</td>\n    <td>A</td>\n    <td align=\"center\">8, 0</td>\n    <td align=\"center\">6, 10</td>\n  </tr>\n  <tr>\n    <td>B</td>\n    <td align=\"center\">6, 0</td>\n    <td align=\"center\">5, 2</td>\n  </tr>\n</table>\n\n<p>1. Write down the best response functions for each player.</p>\n<p>2. Find the Nash equilibria.</p>\n", "solution": "<p>Player 1's best response(s) to Player 2 choosing A are: ['A']</p>\n<p>Player 1's best response(s) to Player 2 choosing B are: ['A']</p>\n<p>Player 2's best response(s) to Player 1 choosing A are: ['B']</p>\n<p>Player 2's best response(s) to Player 1 choosing B are: ['B']</p>\n<p>There are 1 Nash equilibria: [('A', 'B')]</p>"}, {"setup": "\n<p>Consider the 2-player game described by the normal form below:</p>\n<table border=1px align=\"center\">\n  <tr>\n    <td></td>\n    <td></td>\n    <td colspan=2 align=\"center\">Player 2</td>\n  </tr>\n  <tr>\n    <td></td>\n    <td></td>\n    <td align=\"center\">A</td>\n    <td align=\"center\">B</td>\n  <tr>\n    <td rowspan=2>Player 1</td>\n    <td>A</td>\n    <td align=\"center\">1, 9</td>\n    <td align=\"center\">3, 10</td>\n  </tr>\n  <tr>\n    <td>B</td>\n    <td align=\"center\">7, 10</td>\n    <td align=\"center\">5, 6</td>\n  </tr>\n</table>\n\n<p>1. Write down the best response functions for each player.</p>\n<p>2. Find the Nash equilibria.</p>\n", "solution": "<p>Player 1's best response(s) to Player 2 choosing A are: ['B']</p>\n<p>Player 1's best response(s) to Player 2 choosing B are: ['B']</p>\n<p>Player 2's best response(s) to Player 1 choosing A are: ['B']</p>\n<p>Player 2's best response(s) to Player 1 choosing B are: ['A']</p>\n<p>There are 1 Nash equilibria: [('B', 'A')]</p>"}, {"setup": "\n<p>Consider the 2-player game described by the normal form below:</p>\n<table border=1px align=\"center\">\n  <tr>\n    <td></td>\n    <td></td>\n    <td colspan=2 align=\"center\">Player 2</td>\n  </tr>\n  <tr>\n    <td></td>\n    <td></td>\n    <td align=\"center\">A</td>\n    <td align=\"center\">B</td>\n  <tr>\n    <td rowspan=2>Player 1</td>\n    <td>A</td>\n    <td align=\"center\">7, 5</td>\n    <td align=\"center\">0, 5</td>\n  </tr>\n  <tr>\n    <td>B</td>\n    <td align=\"center\">10, 2</td>\n    <td align=\"center\">8, 0</td>\n  </tr>\n</table>\n\n<p>1. Write down the best response functions for each player.</p>\n<p>2. Find the Nash equilibria.</p>\n", "solution": "<p>Player 1's best response(s) to Player 2 choosing A are: ['B']</p>\n<p>Player 1's best response(s) to Player 2 choosing B are: ['B']</p>\n<p>Player 2's best response(s) to Player 1 choosing A are: ['A', 'B']</p>\n<p>Player 2's best response(s) to Player 1 choosing B are: ['A']</p>\n<p>There are 1 Nash equilibria: [('B', 'A')]</p>"}, {"setup": "\n<p>Consider the 2-player game described by the normal form below:</p>\n<table border=1px align=\"center\">\n  <tr>\n    <td></td>\n    <td></td>\n    <td colspan=2 align=\"center\">Player 2</td>\n  </tr>\n  <tr>\n    <td></td>\n    <td></td>\n    <td align=\"center\">A</td>\n    <td align=\"center\">B</td>\n  <tr>\n    <td rowspan=2>Player 1</td>\n    <td>A</td>\n    <td align=\"center\">0, 6</td>\n    <td align=\"center\">8, 9</td>\n  </tr>\n  <tr>\n    <td>B</td>\n    <td align=\"center\">4, 0</td>\n    <td align=\"center\">5, 5</td>\n  </tr>\n</table>\n\n<p>1. Write down the best response functions for each player.</p>\n<p>2. Find the Nash equilibria.</p>\n", "solution": "<p>Player 1's best response(s) to Player 2 choosing A are: ['B']</p>\n<p>Player 1's best response(s) to Player 2 choosing B are: ['A']</p>\n<p>Player 2's best response(s) to Player 1 choosing A are: ['B']</p>\n<p>Player 2's best response(s) to Player 1 choosing B are: ['B']</p>\n<p>There are 1 Nash equilibria: [('A', 'B')]</p>"}, {"setup": "\n<p>Consider the 2-player game described by the normal form below:</p>\n<table border=1px align=\"center\">\n  <tr>\n    <td></td>\n    <td></td>\n    <td colspan=2 align=\"center\">Player 2</td>\n  </tr>\n  <tr>\n    <td></td>\n    <td></td>\n    <td align=\"center\">A</td>\n    <td align=\"center\">B</td>\n  <tr>\n    <td rowspan=2>Player 1</td>\n    <td>A</td>\n    <td align=\"center\">6, 2</td>\n    <td align=\"center\">6, 9</td>\n  </tr>\n  <tr>\n    <td>B</td>\n    <td align=\"center\">4, 2</td>\n    <td align=\"center\">2, 8</td>\n  </tr>\n</table>\n\n<p>1. Write down the best response functions for each player.</p>\n<p>2. Find the Nash equilibria.</p>\n", "solution": "<p>Player 1's best response(s) to Player 2 choosing A are: ['A']</p>\n<p>Player 1's best response(s) to Player 2 choosing B are: ['A']</p>\n<p>Player 2's best response(s) to Player 1 choosing A are: ['B']</p>\n<p>Player 2's best response(s) to Player 1 choosing B are: ['B']</p>\n<p>There are 1 Nash equilibria: [('A', 'B')]</p>"}, {"setup": "\n<p>Consider the 2-player game described by the normal form below:</p>\n<table border=1px align=\"center\">\n  <tr>\n    <td></td>\n    <td></td>\n    <td colspan=2 align=\"center\">Player 2</td>\n  </tr>\n  <tr>\n    <td></td>\n    <td></td>\n    <td align=\"center\">A</td>\n    <td align=\"center\">B</td>\n  <tr>\n    <td rowspan=2>Player 1</td>\n    <td>A</td>\n    <td align=\"center\">7, 1</td>\n    <td align=\"center\">3, 8</td>\n  </tr>\n  <tr>\n    <td>B</td>\n    <td align=\"center\">7, 4</td>\n    <td align=\"center\">10, 4</td>\n  </tr>\n</table>\n\n<p>1. Write down the best response functions for each player.</p>\n<p>2. Find the Nash equilibria.</p>\n", "solution": "<p>Player 1's best response(s) to Player 2 choosing A are: ['A', 'B']</p>\n<p>Player 1's best response(s) to Player 2 choosing B are: ['B']</p>\n<p>Player 2's best response(s) to Player 1 choosing A are: ['B']</p>\n<p>Player 2's best response(s) to Player 1 choosing B are: ['A', 'B']</p>\n<p>There are 2 Nash equilibria: [('B', 'A'), ('B', 'B')]</p>"}, {"setup": "\n<p>Consider the 2-player game described by the normal form below:</p>\n<table border=1px align=\"center\">\n  <tr>\n    <td></td>\n    <td></td>\n    <td colspan=2 align=\"center\">Player 2</td>\n  </tr>\n  <tr>\n    <td></td>\n    <td></td>\n    <td align=\"center\">A</td>\n    <td align=\"center\">B</td>\n  <tr>\n    <td rowspan=2>Player 1</td>\n    <td>A</td>\n    <td align=\"center\">1, 6</td>\n    <td align=\"center\">2, 5</td>\n  </tr>\n  <tr>\n    <td>B</td>\n    <td align=\"center\">9, 5</td>\n    <td align=\"center\">5, 4</td>\n  </tr>\n</table>\n\n<p>1. Write down the best response functions for each player.</p>\n<p>2. Find the Nash equilibria.</p>\n", "solution": "<p>Player 1's best response(s) to Player 2 choosing A are: ['B']</p>\n<p>Player 1's best response(s) to Player 2 choosing B are: ['B']</p>\n<p>Player 2's best response(s) to Player 1 choosing A are: ['A']</p>\n<p>Player 2's best response(s) to Player 1 choosing B are: ['A']</p>\n<p>There are 1 Nash equilibria: [('B', 'A')]</p>"}, {"setup": "\n<p>Consider the 2-player game described by the normal form below:</p>\n<table border=1px align=\"center\">\n  <tr>\n    <td></td>\n    <td></td>\n    <td colspan=2 align=\"center\">Player 2</td>\n  </tr>\n  <tr>\n    <td></td>\n    <td></td>\n    <td align=\"center\">A</td>\n    <td align=\"center\">B</td>\n  <tr>\n    <td rowspan=2>Player 1</td>\n    <td>A</td>\n    <td align=\"center\">3, 10</td>\n    <td align=\"center\">5, 10</td>\n  </tr>\n  <tr>\n    <td>B</td>\n    <td align=\"center\">8, 2</td>\n    <td align=\"center\">0, 0</td>\n  </tr>\n</table>\n\n<p>1. Write down the best response functions for each player.</p>\n<p>2. Find the Nash equilibria.</p>\n", "solution": "<p>Player 1's best response(s) to Player 2 choosing A are: ['B']</p>\n<p>Player 1's best response(s) to Player 2 choosing B are: ['A']</p>\n<p>Player 2's best response(s) to Player 1 choosing A are: ['A', 'B']</p>\n<p>Player 2's best response(s) to Player 1 choosing B are: ['A']</p>\n<p>There are 2 Nash equilibria: [('A', 'B'), ('B', 'A')]</p>"}, {"setup": "\n<p>Consider the 2-player game described by the normal form below:</p>\n<table border=1px align=\"center\">\n  <tr>\n    <td></td>\n    <td></td>\n    <td colspan=2 align=\"center\">Player 2</td>\n  </tr>\n  <tr>\n    <td></td>\n    <td></td>\n    <td align=\"center\">A</td>\n    <td align=\"center\">B</td>\n  <tr>\n    <td rowspan=2>Player 1</td>\n    <td>A</td>\n    <td align=\"center\">8, 0</td>\n    <td align=\"center\">7, 4</td>\n  </tr>\n  <tr>\n    <td>B</td>\n    <td align=\"center\">6, 10</td>\n    <td align=\"center\">4, 10</td>\n  </tr>\n</table>\n\n<p>1. Write down the best response functions for each player.</p>\n<p>2. Find the Nash equilibria.</p>\n", "solution": "<p>Player 1's best response(s) to Player 2 choosing A are: ['A']</p>\n<p>Player 1's best response(s) to Player 2 choosing B are: ['A']</p>\n<p>Player 2's best response(s) to Player 1 choosing A are: ['B']</p>\n<p>Player 2's best response(s) to Player 1 choosing B are: ['A', 'B']</p>\n<p>There are 1 Nash equilibria: [('A', 'B')]</p>"}, {"setup": "\n<p>Consider the 2-player game described by the normal form below:</p>\n<table border=1px align=\"center\">\n  <tr>\n    <td></td>\n    <td></td>\n    <td colspan=2 align=\"center\">Player 2</td>\n  </tr>\n  <tr>\n    <td></td>\n    <td></td>\n    <td align=\"center\">A</td>\n    <td align=\"center\">B</td>\n  <tr>\n    <td rowspan=2>Player 1</td>\n    <td>A</td>\n    <td align=\"center\">0, 2</td>\n    <td align=\"center\">4, 1</td>\n  </tr>\n  <tr>\n    <td>B</td>\n    <td align=\"center\">4, 7</td>\n    <td align=\"center\">1, 2</td>\n  </tr>\n</table>\n\n<p>1. Write down the best response functions for each player.</p>\n<p>2. Find the Nash equilibria.</p>\n", "solution": "<p>Player 1's best response(s) to Player 2 choosing A are: ['B']</p>\n<p>Player 1's best response(s) to Player 2 choosing B are: ['A']</p>\n<p>Player 2's best response(s) to Player 1 choosing A are: ['A']</p>\n<p>Player 2's best response(s) to Player 1 choosing B are: ['A']</p>\n<p>There are 1 Nash equilibria: [('B', 'A')]</p>"}, {"setup": "\n<p>Consider the 2-player game described by the normal form below:</p>\n<table border=1px align=\"center\">\n  <tr>\n    <td></td>\n    <td></td>\n    <td colspan=2 align=\"center\">Player 2</td>\n  </tr>\n  <tr>\n    <td></td>\n    <td></td>\n    <td align=\"center\">A</td>\n    <td align=\"center\">B</td>\n  <tr>\n    <td rowspan=2>Player 1</td>\n    <td>A</td>\n    <td align=\"center\">8, 1</td>\n    <td align=\"center\">10, 8</td>\n  </tr>\n  <tr>\n    <td>B</td>\n    <td align=\"center\">1, 9</td>\n    <td align=\"center\">0, 10</td>\n  </tr>\n</table>\n\n<p>1. Write down the best response functions for each player.</p>\n<p>2. Find the Nash equilibria.</p>\n", "solution": "<p>Player 1's best response(s) to Player 2 choosing A are: ['A']</p>\n<p>Player 1's best response(s) to Player 2 choosing B are: ['A']</p>\n<p>Player 2's best response(s) to Player 1 choosing A are: ['B']</p>\n<p>Player 2's best response(s) to Player 1 choosing B are: ['B']</p>\n<p>There are 1 Nash equilibria: [('A', 'B')]</p>"}, {"setup": "\n<p>Consider the 2-player game described by the normal form below:</p>\n<table border=1px align=\"center\">\n  <tr>\n    <td></td>\n    <td></td>\n    <td colspan=2 align=\"center\">Player 2</td>\n  </tr>\n  <tr>\n    <td></td>\n    <td></td>\n    <td align=\"center\">A</td>\n    <td align=\"center\">B</td>\n  <tr>\n    <td rowspan=2>Player 1</td>\n    <td>A</td>\n    <td align=\"center\">0, 6</td>\n    <td align=\"center\">0, 8</td>\n  </tr>\n  <tr>\n    <td>B</td>\n    <td align=\"center\">6, 0</td>\n    <td align=\"center\">5, 9</td>\n  </tr>\n</table>\n\n<p>1. Write down the best response functions for each player.</p>\n<p>2. Find the Nash equilibria.</p>\n", "solution": "<p>Player 1's best response(s) to Player 2 choosing A are: ['B']</p>\n<p>Player 1's best response(s) to Player 2 choosing B are: ['B']</p>\n<p>Player 2's best response(s) to Player 1 choosing A are: ['B']</p>\n<p>Player 2's best response(s) to Player 1 choosing B are: ['B']</p>\n<p>There are 1 Nash equilibria: [('B', 'B')]</p>"}, {"setup": "\n<p>Consider the 2-player game described by the normal form below:</p>\n<table border=1px align=\"center\">\n  <tr>\n    <td></td>\n    <td></td>\n    <td colspan=2 align=\"center\">Player 2</td>\n  </tr>\n  <tr>\n    <td></td>\n    <td></td>\n    <td align=\"center\">A</td>\n    <td align=\"center\">B</td>\n  <tr>\n    <td rowspan=2>Player 1</td>\n    <td>A</td>\n    <td align=\"center\">4, 8</td>\n    <td align=\"center\">2, 0</td>\n  </tr>\n  <tr>\n    <td>B</td>\n    <td align=\"center\">4, 9</td>\n    <td align=\"center\">10, 7</td>\n  </tr>\n</table>\n\n<p>1. Write down the best response functions for each player.</p>\n<p>2. Find the Nash equilibria.</p>\n", "solution": "<p>Player 1's best response(s) to Player 2 choosing A are: ['A', 'B']</p>\n<p>Player 1's best response(s) to Player 2 choosing B are: ['B']</p>\n<p>Player 2's best response(s) to Player 1 choosing A are: ['A']</p>\n<p>Player 2's best response(s) to Player 1 choosing B are: ['A']</p>\n<p>There are 2 Nash equilibria: [('A', 'A'), ('B', 'A')]</p>"}, {"setup": "\n<p>Consider the 2-player game described by the normal form below:</p>\n<table border=1px align=\"center\">\n  <tr>\n    <td></td>\n    <td></td>\n    <td colspan=2 align=\"center\">Player 2</td>\n  </tr>\n  <tr>\n    <td></td>\n    <td></td>\n    <td align=\"center\">A</td>\n    <td align=\"center\">B</td>\n  <tr>\n    <td rowspan=2>Player 1</td>\n    <td>A</td>\n    <td align=\"center\">3, 1</td>\n    <td align=\"center\">7, 2</td>\n  </tr>\n  <tr>\n    <td>B</td>\n    <td align=\"center\">3, 3</td>\n    <td align=\"center\">6, 6</td>\n  </tr>\n</table>\n\n<p>1. Write down the best response functions for each player.</p>\n<p>2. Find the Nash equilibria.</p>\n", "solution": "<p>Player 1's best response(s) to Player 2 choosing A are: ['A', 'B']</p>\n<p>Player 1's best response(s) to Player 2 choosing B are: ['A']</p>\n<p>Player 2's best response(s) to Player 1 choosing A are: ['B']</p>\n<p>Player 2's best response(s) to Player 1 choosing B are: ['B']</p>\n<p>There are 1 Nash equilibria: [('A', 'B')]</p>"}, {"setup": "\n<p>Consider the 2-player game described by the normal form below:</p>\n<table border=1px align=\"center\">\n  <tr>\n    <td></td>\n    <td></td>\n    <td colspan=2 align=\"center\">Player 2</td>\n  </tr>\n  <tr>\n    <td></td>\n    <td></td>\n    <td align=\"center\">A</td>\n    <td align=\"center\">B</td>\n  <tr>\n    <td rowspan=2>Player 1</td>\n    <td>A</td>\n    <td align=\"center\">4, 7</td>\n    <td align=\"center\">1, 2</td>\n  </tr>\n  <tr>\n    <td>B</td>\n    <td align=\"center\">8, 3</td>\n    <td align=\"center\">5, 4</td>\n  </tr>\n</table>\n\n<p>1. Write down the best response functions for each player.</p>\n<p>2. Find the Nash equilibria.</p>\n", "solution": "<p>Player 1's best response(s) to Player 2 choosing A are: ['B']</p>\n<p>Player 1's best response(s) to Player 2 choosing B are: ['B']</p>\n<p>Player 2's best response(s) to Player 1 choosing A are: ['A']</p>\n<p>Player 2's best response(s) to Player 1 choosing B are: ['B']</p>\n<p>There are 1 Nash equilibria: [('B', 'B')]</p>"}, {"setup": "\n<p>Consider the 2-player game described by the normal form below:</p>\n<table border=1px align=\"center\">\n  <tr>\n    <td></td>\n    <td></td>\n    <td colspan=3 align=\"center\">Player 2</td>\n  </tr>\n  <tr>\n    <td></td>\n    <td></td>\n    <td align=\"center\">A</td>\n    <td align=\"center\">B</td>\n    <td align=\"center\">C</td>\n  <tr>\n    <td rowspan=3>Player 1</td>\n    <td>A</td>\n    <td align=\"center\">9, 3</td>\n    <td align=\"center\">1, 7</td>\n    <td align=\"center\">9, 7</td>\n  </tr>\n  <tr>\n    <td>B</td>\n    <td align=\"center\">8, 10</td>\n    <td align=\"center\">6, 5</td>\n    <td align=\"center\">2, 0</td>\n  </tr>\n  <tr>\n    <td>C</td>\n    <td align=\"center\">10, 10</td>\n    <td align=\"center\">4, 3</td>\n    <td align=\"center\">9, 3</td>\n  </tr>\n</table>\n\n<p>1. Write down the best response functions for each player.</p>\n<p>2. Find the Nash equilibria.</p>\n", "solution": "<p>Player 1's best response(s) to Player 2 choosing A are: ['C']</p>\n<p>Player 1's best response(s) to Player 2 choosing B are: ['B']</p>\n<p>Player 1's best response(s) to Player 2 choosing C are: ['A', 'C']</p>\n<p>Player 2's best response(s) to Player 1 choosing A are: ['B', 'C']</p>\n<p>Player 2's best response(s) to Player 1 choosing B are: ['A']</p>\n<p>Player 2's best response(s) to Player 1 choosing C are: ['A']</p>\n<p>There are 2 Nash equilibria: [('A', 'C'), ('C', 'A')]</p>"}, {"setup": "\n<p>Consider the 2-player game described by the normal form below:</p>\n<table border=1px align=\"center\">\n  <tr>\n    <td></td>\n    <td></td>\n    <td colspan=3 align=\"center\">Player 2</td>\n  </tr>\n  <tr>\n    <td></td>\n    <td></td>\n    <td align=\"center\">A</td>\n    <td align=\"center\">B</td>\n    <td align=\"center\">C</td>\n  <tr>\n    <td rowspan=3>Player 1</td>\n    <td>A</td>\n    <td align=\"center\">5, 7</td>\n    <td align=\"center\">2, 9</td>\n    <td align=\"center\">0, 9</td>\n  </tr>\n  <tr>\n    <td>B</td>\n    <td align=\"center\">1, 3</td>\n    <td align=\"center\">5, 8</td>\n    <td align=\"center\">9, 4</td>\n  </tr>\n  <tr>\n    <td>C</td>\n    <td align=\"center\">2, 3</td>\n    <td align=\"center\">4, 8</td>\n    <td align=\"center\">10, 4</td>\n  </tr>\n</table>\n\n<p>1. Write down the best response functions for each player.</p>\n<p>2. Find the Nash equilibria.</p>\n", "solution": "<p>Player 1's best response(s) to Player 2 choosing A are: ['A']</p>\n<p>Player 1's best response(s) to Player 2 choosing B are: ['B']</p>\n<p>Player 1's best response(s) to Player 2 choosing C are: ['C']</p>\n<p>Player 2's best response(s) to Player 1 choosing A are: ['B', 'C']</p>\n<p>Player 2's best response(s) to Player 1 choosing B are: ['B']</p>\n<p>Player 2's best response(s) to Player 1 choosing C are: ['B']</p>\n<p>There are 1 Nash equilibria: [('B', 'B')]</p>"}, {"setup": "\n<p>Consider the 2-player game described by the normal form below:</p>\n<table border=1px align=\"center\">\n  <tr>\n    <td></td>\n    <td></td>\n    <td colspan=3 align=\"center\">Player 2</td>\n  </tr>\n  <tr>\n    <td></td>\n    <td></td>\n    <td align=\"center\">A</td>\n    <td align=\"center\">B</td>\n    <td align=\"center\">C</td>\n  <tr>\n    <td rowspan=3>Player 1</td>\n    <td>A</td>\n    <td align=\"center\">3, 5</td>\n    <td align=\"center\">4, 10</td>\n    <td align=\"center\">7, 10</td>\n  </tr>\n  <tr>\n    <td>B</td>\n    <td align=\"center\">3, 4</td>\n    <td align=\"center\">3, 6</td>\n    <td align=\"center\">9, 10</td>\n  </tr>\n  <tr>\n    <td>C</td>\n    <td align=\"center\">10, 7</td>\n    <td align=\"center\">5, 1</td>\n    <td align=\"center\">0, 9</td>\n  </tr>\n</table>\n\n<p>1. Write down the best response functions for each player.</p>\n<p>2. Find the Nash equilibria.</p>\n", "solution": "<p>Player 1's best response(s) to Player 2 choosing A are: ['C']</p>\n<p>Player 1's best response(s) to Player 2 choosing B are: ['C']</p>\n<p>Player 1's best response(s) to Player 2 choosing C are: ['B']</p>\n<p>Player 2's best response(s) to Player 1 choosing A are: ['B', 'C']</p>\n<p>Player 2's best response(s) to Player 1 choosing B are: ['C']</p>\n<p>Player 2's best response(s) to Player 1 choosing C are: ['C']</p>\n<p>There are 1 Nash equilibria: [('B', 'C')]</p>"}, {"setup": "\n<p>Consider the 2-player game described by the normal form below:</p>\n<table border=1px align=\"center\">\n  <tr>\n    <td></td>\n    <td></td>\n    <td colspan=3 align=\"center\">Player 2</td>\n  </tr>\n  <tr>\n    <td></td>\n    <td></td>\n    <td align=\"center\">A</td>\n    <td align=\"center\">B</td>\n    <td align=\"center\">C</td>\n  <tr>\n    <td rowspan=3>Player 1</td>\n    <td>A</td>\n    <td align=\"center\">0, 6</td>\n    <td align=\"center\">1, 6</td>\n    <td align=\"center\">5, 5</td>\n  </tr>\n  <tr>\n    <td>B</td>\n    <td align=\"center\">7, 2</td>\n    <td align=\"center\">2, 5</td>\n    <td align=\"center\">10, 7</td>\n  </tr>\n  <tr>\n    <td>C</td>\n    <td align=\"center\">9, 10</td>\n    <td align=\"center\">5, 5</td>\n    <td align=\"center\">4, 1</td>\n  </tr>\n</table>\n\n<p>1. Write down the best response functions for each player.</p>\n<p>2. Find the Nash equilibria.</p>\n", "solution": "<p>Player 1's best response(s) to Player 2 choosing A are: ['C']</p>\n<p>Player 1's best response(s) to Player 2 choosing B are: ['C']</p>\n<p>Player 1's best response(s) to Player 2 choosing C are: ['B']</p>\n<p>Player 2's best response(s) to Player 1 choosing A are: ['A', 'B']</p>\n<p>Player 2's best response(s) to Player 1 choosing B are: ['C']</p>\n<p>Player 2's best response(s) to Player 1 choosing C are: ['A']</p>\n<p>There are 2 Nash equilibria: [('B', 'C'), ('C', 'A')]</p>"}, {"setup": "\n<p>Consider the 2-player game described by the normal form below:</p>\n<table border=1px align=\"center\">\n  <tr>\n    <td></td>\n    <td></td>\n    <td colspan=3 align=\"center\">Player 2</td>\n  </tr>\n  <tr>\n    <td></td>\n    <td></td>\n    <td align=\"center\">A</td>\n    <td align=\"center\">B</td>\n    <td align=\"center\">C</td>\n  <tr>\n    <td rowspan=3>Player 1</td>\n    <td>A</td>\n    <td align=\"center\">8, 7</td>\n    <td align=\"center\">7, 9</td>\n    <td align=\"center\">5, 4</td>\n  </tr>\n  <tr>\n    <td>B</td>\n    <td align=\"center\">7, 2</td>\n    <td align=\"center\">5, 8</td>\n    <td align=\"center\">2, 9</td>\n  </tr>\n  <tr>\n    <td>C</td>\n    <td align=\"center\">6, 4</td>\n    <td align=\"center\">10, 6</td>\n    <td align=\"center\">7, 0</td>\n  </tr>\n</table>\n\n<p>1. Write down the best response functions for each player.</p>\n<p>2. Find the Nash equilibria.</p>\n", "solution": "<p>Player 1's best response(s) to Player 2 choosing A are: ['A']</p>\n<p>Player 1's best response(s) to Player 2 choosing B are: ['C']</p>\n<p>Player 1's best response(s) to Player 2 choosing C are: ['C']</p>\n<p>Player 2's best response(s) to Player 1 choosing A are: ['B']</p>\n<p>Player 2's best response(s) to Player 1 choosing B are: ['C']</p>\n<p>Player 2's best response(s) to Player 1 choosing C are: ['B']</p>\n<p>There are 1 Nash equilibria: [('C', 'B')]</p>"}, {"setup": "\n<p>Consider the 2-player game described by the normal form below:</p>\n<table border=1px align=\"center\">\n  <tr>\n    <td></td>\n    <td></td>\n    <td colspan=3 align=\"center\">Player 2</td>\n  </tr>\n  <tr>\n    <td></td>\n    <td></td>\n    <td align=\"center\">A</td>\n    <td align=\"center\">B</td>\n    <td align=\"center\">C</td>\n  <tr>\n    <td rowspan=3>Player 1</td>\n    <td>A</td>\n    <td align=\"center\">3, 10</td>\n    <td align=\"center\">0, 2</td>\n    <td align=\"center\">5, 4</td>\n  </tr>\n  <tr>\n    <td>B</td>\n    <td align=\"center\">3, 2</td>\n    <td align=\"center\">8, 0</td>\n    <td align=\"center\">1, 8</td>\n  </tr>\n  <tr>\n    <td>C</td>\n    <td align=\"center\">5, 9</td>\n    <td align=\"center\">5, 1</td>\n    <td align=\"center\">4, 9</td>\n  </tr>\n</table>\n\n<p>1. Write down the best response functions for each player.</p>\n<p>2. Find the Nash equilibria.</p>\n", "solution": "<p>Player 1's best response(s) to Player 2 choosing A are: ['C']</p>\n<p>Player 1's best response(s) to Player 2 choosing B are: ['B']</p>\n<p>Player 1's best response(s) to Player 2 choosing C are: ['A']</p>\n<p>Player 2's best response(s) to Player 1 choosing A are: ['A']</p>\n<p>Player 2's best response(s) to Player 1 choosing B are: ['C']</p>\n<p>Player 2's best response(s) to Player 1 choosing C are: ['A', 'C']</p>\n<p>There are 1 Nash equilibria: [('C', 'A')]</p>"}, {"setup": "\n<p>Consider the 2-player game described by the normal form below:</p>\n<table border=1px align=\"center\">\n  <tr>\n    <td></td>\n    <td></td>\n    <td colspan=3 align=\"center\">Player 2</td>\n  </tr>\n  <tr>\n    <td></td>\n    <td></td>\n    <td align=\"center\">A</td>\n    <td align=\"center\">B</td>\n    <td align=\"center\">C</td>\n  <tr>\n    <td rowspan=3>Player 1</td>\n    <td>A</td>\n    <td align=\"center\">6, 1</td>\n    <td align=\"center\">3, 3</td>\n    <td align=\"center\">8, 3</td>\n  </tr>\n  <tr>\n    <td>B</td>\n    <td align=\"center\">8, 6</td>\n    <td align=\"center\">2, 0</td>\n    <td align=\"center\">3, 6</td>\n  </tr>\n  <tr>\n    <td>C</td>\n    <td align=\"center\">3, 2</td>\n    <td align=\"center\">1, 4</td>\n    <td align=\"center\">8, 2</td>\n  </tr>\n</table>\n\n<p>1. Write down the best response functions for each player.</p>\n<p>2. Find the Nash equilibria.</p>\n", "solution": "<p>Player 1's best response(s) to Player 2 choosing A are: ['B']</p>\n<p>Player 1's best response(s) to Player 2 choosing B are: ['A']</p>\n<p>Player 1's best response(s) to Player 2 choosing C are: ['A', 'C']</p>\n<p>Player 2's best response(s) to Player 1 choosing A are: ['B', 'C']</p>\n<p>Player 2's best response(s) to Player 1 choosing B are: ['A', 'C']</p>\n<p>Player 2's best response(s) to Player 1 choosing C are: ['B']</p>\n<p>There are 3 Nash equilibria: [('A', 'B'), ('A', 'C'), ('B', 'A')]</p>"}, {"setup": "\n<p>Consider the 2-player game described by the normal form below:</p>\n<table border=1px align=\"center\">\n  <tr>\n    <td></td>\n    <td></td>\n    <td colspan=3 align=\"center\">Player 2</td>\n  </tr>\n  <tr>\n    <td></td>\n    <td></td>\n    <td align=\"center\">A</td>\n    <td align=\"center\">B</td>\n    <td align=\"center\">C</td>\n  <tr>\n    <td rowspan=3>Player 1</td>\n    <td>A</td>\n    <td align=\"center\">8, 3</td>\n    <td align=\"center\">5, 5</td>\n    <td align=\"center\">8, 4</td>\n  </tr>\n  <tr>\n    <td>B</td>\n    <td align=\"center\">8, 4</td>\n    <td align=\"center\">8, 9</td>\n    <td align=\"center\">1, 10</td>\n  </tr>\n  <tr>\n    <td>C</td>\n    <td align=\"center\">7, 1</td>\n    <td align=\"center\">7, 6</td>\n    <td align=\"center\">0, 5</td>\n  </tr>\n</table>\n\n<p>1. Write down the best response functions for each player.</p>\n<p>2. Find the Nash equilibria.</p>\n", "solution": "<p>Player 1's best response(s) to Player 2 choosing A are: ['A', 'B']</p>\n<p>Player 1's best response(s) to Player 2 choosing B are: ['B']</p>\n<p>Player 1's best response(s) to Player 2 choosing C are: ['A']</p>\n<p>Player 2's best response(s) to Player 1 choosing A are: ['B']</p>\n<p>Player 2's best response(s) to Player 1 choosing B are: ['C']</p>\n<p>Player 2's best response(s) to Player 1 choosing C are: ['B']</p>\n<p>There are 0 Nash equilibria: []</p>"}, {"setup": "\n<p>Consider the 2-player game described by the normal form below:</p>\n<table border=1px align=\"center\">\n  <tr>\n    <td></td>\n    <td></td>\n    <td colspan=3 align=\"center\">Player 2</td>\n  </tr>\n  <tr>\n    <td></td>\n    <td></td>\n    <td align=\"center\">A</td>\n    <td align=\"center\">B</td>\n    <td align=\"center\">C</td>\n  <tr>\n    <td rowspan=3>Player 1</td>\n    <td>A</td>\n    <td align=\"center\">9, 1</td>\n    <td align=\"center\">10, 1</td>\n    <td align=\"center\">5, 3</td>\n  </tr>\n  <tr>\n    <td>B</td>\n    <td align=\"center\">0, 9</td>\n    <td align=\"center\">4, 10</td>\n    <td align=\"center\">10, 0</td>\n  </tr>\n  <tr>\n    <td>C</td>\n    <td align=\"center\">4, 9</td>\n    <td align=\"center\">10, 10</td>\n    <td align=\"center\">4, 1</td>\n  </tr>\n</table>\n\n<p>1. Write down the best response functions for each player.</p>\n<p>2. Find the Nash equilibria.</p>\n", "solution": "<p>Player 1's best response(s) to Player 2 choosing A are: ['A']</p>\n<p>Player 1's best response(s) to Player 2 choosing B are: ['A', 'C']</p>\n<p>Player 1's best response(s) to Player 2 choosing C are: ['B']</p>\n<p>Player 2's best response(s) to Player 1 choosing A are: ['C']</p>\n<p>Player 2's best response(s) to Player 1 choosing B are: ['B']</p>\n<p>Player 2's best response(s) to Player 1 choosing C are: ['B']</p>\n<p>There are 1 Nash equilibria: [('C', 'B')]</p>"}, {"setup": "\n<p>Consider the 2-player game described by the normal form below:</p>\n<table border=1px align=\"center\">\n  <tr>\n    <td></td>\n    <td></td>\n    <td colspan=3 align=\"center\">Player 2</td>\n  </tr>\n  <tr>\n    <td></td>\n    <td></td>\n    <td align=\"center\">A</td>\n    <td align=\"center\">B</td>\n    <td align=\"center\">C</td>\n  <tr>\n    <td rowspan=3>Player 1</td>\n    <td>A</td>\n    <td align=\"center\">4, 3</td>\n    <td align=\"center\">2, 7</td>\n    <td align=\"center\">8, 3</td>\n  </tr>\n  <tr>\n    <td>B</td>\n    <td align=\"center\">10, 6</td>\n    <td align=\"center\">6, 0</td>\n    <td align=\"center\">2, 0</td>\n  </tr>\n  <tr>\n    <td>C</td>\n    <td align=\"center\">9, 8</td>\n    <td align=\"center\">6, 0</td>\n    <td align=\"center\">4, 8</td>\n  </tr>\n</table>\n\n<p>1. Write down the best response functions for each player.</p>\n<p>2. Find the Nash equilibria.</p>\n", "solution": "<p>Player 1's best response(s) to Player 2 choosing A are: ['B']</p>\n<p>Player 1's best response(s) to Player 2 choosing B are: ['B', 'C']</p>\n<p>Player 1's best response(s) to Player 2 choosing C are: ['A']</p>\n<p>Player 2's best response(s) to Player 1 choosing A are: ['B']</p>\n<p>Player 2's best response(s) to Player 1 choosing B are: ['A']</p>\n<p>Player 2's best response(s) to Player 1 choosing C are: ['A', 'C']</p>\n<p>There are 1 Nash equilibria: [('B', 'A')]</p>"}, {"setup": "\n<p>Consider the 2-player game described by the normal form below:</p>\n<table border=1px align=\"center\">\n  <tr>\n    <td></td>\n    <td></td>\n    <td colspan=3 align=\"center\">Player 2</td>\n  </tr>\n  <tr>\n    <td></td>\n    <td></td>\n    <td align=\"center\">A</td>\n    <td align=\"center\">B</td>\n    <td align=\"center\">C</td>\n  <tr>\n    <td rowspan=3>Player 1</td>\n    <td>A</td>\n    <td align=\"center\">3, 9</td>\n    <td align=\"center\">1, 0</td>\n    <td align=\"center\">4, 9</td>\n  </tr>\n  <tr>\n    <td>B</td>\n    <td align=\"center\">0, 10</td>\n    <td align=\"center\">0, 10</td>\n    <td align=\"center\">2, 5</td>\n  </tr>\n  <tr>\n    <td>C</td>\n    <td align=\"center\">1, 0</td>\n    <td align=\"center\">0, 10</td>\n    <td align=\"center\">2, 10</td>\n  </tr>\n</table>\n\n<p>1. Write down the best response functions for each player.</p>\n<p>2. Find the Nash equilibria.</p>\n", "solution": "<p>Player 1's best response(s) to Player 2 choosing A are: ['A']</p>\n<p>Player 1's best response(s) to Player 2 choosing B are: ['A']</p>\n<p>Player 1's best response(s) to Player 2 choosing C are: ['A']</p>\n<p>Player 2's best response(s) to Player 1 choosing A are: ['A', 'C']</p>\n<p>Player 2's best response(s) to Player 1 choosing B are: ['A', 'B']</p>\n<p>Player 2's best response(s) to Player 1 choosing C are: ['B', 'C']</p>\n<p>There are 2 Nash equilibria: [('A', 'A'), ('A', 'C')]</p>"}, {"setup": "\n<p>Consider the 2-player game described by the normal form below:</p>\n<table border=1px align=\"center\">\n  <tr>\n    <td></td>\n    <td></td>\n    <td colspan=3 align=\"center\">Player 2</td>\n  </tr>\n  <tr>\n    <td></td>\n    <td></td>\n    <td align=\"center\">A</td>\n    <td align=\"center\">B</td>\n    <td align=\"center\">C</td>\n  <tr>\n    <td rowspan=3>Player 1</td>\n    <td>A</td>\n    <td align=\"center\">6, 2</td>\n    <td align=\"center\">1, 3</td>\n    <td align=\"center\">5, 4</td>\n  </tr>\n  <tr>\n    <td>B</td>\n    <td align=\"center\">9, 0</td>\n    <td align=\"center\">3, 6</td>\n    <td align=\"center\">4, 6</td>\n  </tr>\n  <tr>\n    <td>C</td>\n    <td align=\"center\">10, 7</td>\n    <td align=\"center\">8, 5</td>\n    <td align=\"center\">9, 8</td>\n  </tr>\n</table>\n\n<p>1. Write down the best response functions for each player.</p>\n<p>2. Find the Nash equilibria.</p>\n", "solution": "<p>Player 1's best response(s) to Player 2 choosing A are: ['C']</p>\n<p>Player 1's best response(s) to Player 2 choosing B are: ['C']</p>\n<p>Player 1's best response(s) to Player 2 choosing C are: ['C']</p>\n<p>Player 2's best response(s) to Player 1 choosing A are: ['C']</p>\n<p>Player 2's best response(s) to Player 1 choosing B are: ['B', 'C']</p>\n<p>Player 2's best response(s) to Player 1 choosing C are: ['C']</p>\n<p>There are 1 Nash equilibria: [('C', 'C')]</p>"}, {"setup": "\n<p>Consider the 2-player game described by the normal form below:</p>\n<table border=1px align=\"center\">\n  <tr>\n    <td></td>\n    <td></td>\n    <td colspan=3 align=\"center\">Player 2</td>\n  </tr>\n  <tr>\n    <td></td>\n    <td></td>\n    <td align=\"center\">A</td>\n    <td align=\"center\">B</td>\n    <td align=\"center\">C</td>\n  <tr>\n    <td rowspan=3>Player 1</td>\n    <td>A</td>\n    <td align=\"center\">3, 4</td>\n    <td align=\"center\">1, 1</td>\n    <td align=\"center\">9, 7</td>\n  </tr>\n  <tr>\n    <td>B</td>\n    <td align=\"center\">1, 2</td>\n    <td align=\"center\">0, 9</td>\n    <td align=\"center\">6, 2</td>\n  </tr>\n  <tr>\n    <td>C</td>\n    <td align=\"center\">1, 5</td>\n    <td align=\"center\">10, 8</td>\n    <td align=\"center\">7, 2</td>\n  </tr>\n</table>\n\n<p>1. Write down the best response functions for each player.</p>\n<p>2. Find the Nash equilibria.</p>\n", "solution": "<p>Player 1's best response(s) to Player 2 choosing A are: ['A']</p>\n<p>Player 1's best response(s) to Player 2 choosing B are: ['C']</p>\n<p>Player 1's best response(s) to Player 2 choosing C are: ['A']</p>\n<p>Player 2's best response(s) to Player 1 choosing A are: ['C']</p>\n<p>Player 2's best response(s) to Player 1 choosing B are: ['B']</p>\n<p>Player 2's best response(s) to Player 1 choosing C are: ['B']</p>\n<p>There are 2 Nash equilibria: [('A', 'C'), ('C', 'B')]</p>"}, {"setup": "\n<p>Consider the 2-player game described by the normal form below:</p>\n<table border=1px align=\"center\">\n  <tr>\n    <td></td>\n    <td></td>\n    <td colspan=3 align=\"center\">Player 2</td>\n  </tr>\n  <tr>\n    <td></td>\n    <td></td>\n    <td align=\"center\">A</td>\n    <td align=\"center\">B</td>\n    <td align=\"center\">C</td>\n  <tr>\n    <td rowspan=3>Player 1</td>\n    <td>A</td>\n    <td align=\"center\">4, 10</td>\n    <td align=\"center\">9, 1</td>\n    <td align=\"center\">1, 4</td>\n  </tr>\n  <tr>\n    <td>B</td>\n    <td align=\"center\">1, 0</td>\n    <td align=\"center\">7, 1</td>\n    <td align=\"center\">10, 9</td>\n  </tr>\n  <tr>\n    <td>C</td>\n    <td align=\"center\">10, 8</td>\n    <td align=\"center\">7, 4</td>\n    <td align=\"center\">7, 3</td>\n  </tr>\n</table>\n\n<p>1. Write down the best response functions for each player.</p>\n<p>2. Find the Nash equilibria.</p>\n", "solution": "<p>Player 1's best response(s) to Player 2 choosing A are: ['C']</p>\n<p>Player 1's best response(s) to Player 2 choosing B are: ['A']</p>\n<p>Player 1's best response(s) to Player 2 choosing C are: ['B']</p>\n<p>Player 2's best response(s) to Player 1 choosing A are: ['A']</p>\n<p>Player 2's best response(s) to Player 1 choosing B are: ['C']</p>\n<p>Player 2's best response(s) to Player 1 choosing C are: ['A']</p>\n<p>There are 2 Nash equilibria: [('B', 'C'), ('C', 'A')]</p>"}, {"setup": "\n<p>Consider the 2-player game described by the normal form below:</p>\n<table border=1px align=\"center\">\n  <tr>\n    <td></td>\n    <td></td>\n    <td colspan=3 align=\"center\">Player 2</td>\n  </tr>\n  <tr>\n    <td></td>\n    <td></td>\n    <td align=\"center\">A</td>\n    <td align=\"center\">B</td>\n    <td align=\"center\">C</td>\n  <tr>\n    <td rowspan=3>Player 1</td>\n    <td>A</td>\n    <td align=\"center\">8, 2</td>\n    <td align=\"center\">0, 3</td>\n    <td align=\"center\">3, 2</td>\n  </tr>\n  <tr>\n    <td>B</td>\n    <td align=\"center\">6, 3</td>\n    <td align=\"center\">9, 7</td>\n    <td align=\"center\">0, 6</td>\n  </tr>\n  <tr>\n    <td>C</td>\n    <td align=\"center\">6, 1</td>\n    <td align=\"center\">6, 8</td>\n    <td align=\"center\">8, 2</td>\n  </tr>\n</table>\n\n<p>1. Write down the best response functions for each player.</p>\n<p>2. Find the Nash equilibria.</p>\n", "solution": "<p>Player 1's best response(s) to Player 2 choosing A are: ['A']</p>\n<p>Player 1's best response(s) to Player 2 choosing B are: ['B']</p>\n<p>Player 1's best response(s) to Player 2 choosing C are: ['C']</p>\n<p>Player 2's best response(s) to Player 1 choosing A are: ['B']</p>\n<p>Player 2's best response(s) to Player 1 choosing B are: ['B']</p>\n<p>Player 2's best response(s) to Player 1 choosing C are: ['B']</p>\n<p>There are 1 Nash equilibria: [('B', 'B')]</p>"}]